# FileNames : <zen_ezz>
# Python Bytecode : 3.8.5
# Selector <module> In Line 1 file out.pyc
# Timestamp In Code :  (2020-08-24 02:27:49)

# Method Name:       <module>
# Filename:          <zen_ezz>
# Argument count:    0
# Position-only argument count: 0
# Keyword-only arguments: 0
# Number of locals:  0
# Stack size:        9
# Flags:             0x00000040 (NOFREE)
# First Line:        1
# Constants:
#    0: 0
#    1: ('TelegramClient', 'sync', 'events')
#    2: ('GetHistoryRequest', 'GetBotCallbackAnswerRequest')
#    3: ('SessionPasswordNeededError',)
#    4: ('sleep',)
#    5: ('BeautifulSoup',)
#    6: None
#    7: 'cfg.json'
#    8: 'r'
#    9: 'walletltc'
#   10: 'walletdoge'
#   11: 'walletzec'
#   12: 'walletbch'
#   13: 'walletbtc'
#   14: <code object mengetik at 0xae3a56a0, file "<zen_ezz>", line 16>
#   15: 'mengetik'
#   16: <code object tunggu at 0xae5a7df0, file "<zen_ezz>", line 22>
#   17: 'tunggu'
#   18: '\x1b[1;35m\n                                              \neeeee  eeeee e    e eeee eeeee       e  eeeee \n8   8  8   8 8    8 8    "   8       8  8   8 \n8eee8e 8eee8 8eeee8 8eee eeee8       8e 8e  8 \n88   8 88  8   88   88   88          88 88  8 \n88   8 88  8   88   88ee 88ee8       88 88ee8 \n                               eeeee\n\x1b[1;36m=============================================\n\x1b[1;32m ~ anthesphong1998@gmail.com - t.me/rayez_id   \n\x1b[1;36m=============================================\n'
#   19: 'clear'
#   20: '\x1b[1;35mCONFIGURATION SETTING \x1b[1;36m: AUTO VISIT & WD CLICKBOT'
#   21: <code object password at 0xae33b708, file "<zen_ezz>", line 48>
#   22: 'password'
#   23: '\x1b[1;35mINPUT CURRENCY        \x1b[1;36m: '
#   24: 'doge'
#   25: 'ltc'
#   26: 'zec'
#   27: 'btc'
#   28: 'bch'
#   29: '\n\n\n\n\n\n\n\n\n\n\n\n\n\n\n\n\n\n\n\n\n\n\n\n\n\n\n\n\n\n\n\n\n\n\n\n\n\n\n\n\n\n\n\n\n\n\n\n\n\n\n\n\n\n\n\n\n\n\n\n'
#   30: '\x1b[1;35mSTATUS                \x1b[1;36m: Wrong Input \n'
#   31: False
#   32: <code object animate at 0xae33b840, file "<zen_ezz>", line 81>
#   33: 'animate'
#   34: ('target',)
#   35: 2
#   36: True
#   37: ' Jangan lupa bahagia, tersenyumlah =)'
#   38: ''
#   39: ('end',)
#   40: 0.1
#   41: '\n'
#   42: 'session'
#   43: 'https://ipinfo.io/json'
#   44: '\x1b[1;35mYOUR LOCATION\t: \x1b[1;36m{1}\t({2})\n\x1b[1;35mYOUR OWN IP\t: \x1b[1;36m{0}'
#   45: 'ip'
#   46: '[NO DATA]'
#   47: 'region'
#   48: 'country'
#   49: '\x1b[1;35mWELCOME TO BOT  :\x1b[1;36m Visit and Withdraw Clickbot\n\x1b[1;35mNOTE            :\x1b[1;36m This Script Is not for sale !\n'
#   50: 'User-Agent'
#   51: 'Mozilla/5.0 (Windows NT 10.0; Win32; x86) AppleWebKit/537.36 (KHTML, like Gecko) Chrome/67.0.3396.99 Safari/537.36'
#   52: 800812
#   53: 'db55ad67a98df35667ca788b97f771f5'
#   54: <code object withdraw at 0xae33b8a8, file "<zen_ezz>", line 118>
#   55: 'withdraw'
#   56: <code object visit at 0xae33b910, file "<zen_ezz>", line 144>
#   57: 'visit'
#   58: 'list.txt'
#   59: '\x1b[1;36m===============================================\n'
#   60: '\x1b[1;35mYOUR NUMBER     : \x1b[1;36m'
#   61: 'session/'
#   62: '\x1b[1;35mVERIF CODE      : \x1b[1;36m'
#   63: '\x1b[1;35m2FA CODE        : \x1b[1;36m'
#   64: '\r\x1b[1;35mSTATUS          : \x1b[1;36mSomething Wrong happened !\n'
#   65: '@Dogecoin_click_bot'
#   66: 'DOGE'
#   67: '@Litecoin_click_bot'
#   68: 'LTC'
#   69: '@Zcash_click_bot'
#   70: 'ZEC'
#   71: '@BCH_clickbot'
#   72: 'BCH'
#   73: '@BitcoinClick_bot'
#   74: 'BTC'
#   75: '\r\x1b[1;35mSTATUS AKUN     : \x1b[1;36mSomething Wrong happened !\n\n'
#   76: 1
# Names:
#    0: telethon
#    1: TelegramClient
#    2: sync
#    3: events
#    4: telethon.tl.functions.messages
#    5: GetHistoryRequest
#    6: GetBotCallbackAnswerRequest
#    7: telethon.errors
#    8: SessionPasswordNeededError
#    9: time
#   10: sleep
#   11: bs4
#   12: BeautifulSoup
#   13: re
#   14: sys
#   15: os
#   16: colorama
#   17: random
#   18: json
#   19: threading
#   20: itertools
#   21: requests
#   22: open
#   23: fh
#   24: read
#   25: json_str
#   26: loads
#   27: json_value
#   28: ltcwallet
#   29: dogewallet
#   30: zecwallet
#   31: bchwallet
#   32: btcwallet
#   33: mengetik
#   34: tunggu
#   35: banner
#   36: system
#   37: print
#   38: password
#   39: input
#   40: currency
#   41: exit
#   42: ansi
#   43: clear_screen
#   44: done
#   45: animate
#   46: Thread
#   47: t
#   48: start
#   49: lines
#   50: line
#   51: c
#   52: stdout
#   53: flush
#   54: path
#   55: exists
#   56: makedirs
#   57: get
#   58: r
#   59: text
#   60: data
#   61: format
#   62: ua
#   63: api_id
#   64: api_hash
#   65: withdraw
#   66: visit
#   67: f
#   68: len
#   69: readlines
#   70: baris
#   71: close
#   72: range
#   73: i
#   74: strip
#   75: phone_number
#   76: client
#   77: connect
#   78: is_user_authorized
#   79: send_code_request
#   80: sign_in
#   81: me
#   82: passw
#   83: Exception
#   84: write
#   85: get_me
#   86: myself
#   87: disconnect
#   88: get_entity
#   89: channel_entity
#   90: channel_username
#   91: cr
#   92: wallet
  1           0 LOAD_CONST               0 (0)
              2 LOAD_CONST               1 (('TelegramClient', 'sync', 'events'))
              4 IMPORT_NAME              0 (telethon)
              6 IMPORT_FROM              1 (TelegramClient)
              8 STORE_NAME               1 (TelegramClient)
             10 IMPORT_FROM              2 (sync)
             12 STORE_NAME               2 (sync)
             14 IMPORT_FROM              3 (events)
             16 STORE_NAME               3 (events)
             18 POP_TOP

  2          20 LOAD_CONST               0 (0)
             22 LOAD_CONST               2 (('GetHistoryRequest', 'GetBotCallbackAnswerRequest'))
             24 IMPORT_NAME              4 (telethon.tl.functions.messages)
             26 IMPORT_FROM              5 (GetHistoryRequest)
             28 STORE_NAME               5 (GetHistoryRequest)
             30 IMPORT_FROM              6 (GetBotCallbackAnswerRequest)
             32 STORE_NAME               6 (GetBotCallbackAnswerRequest)
             34 POP_TOP

  3          36 LOAD_CONST               0 (0)
             38 LOAD_CONST               3 (('SessionPasswordNeededError',))
             40 IMPORT_NAME              7 (telethon.errors)
             42 IMPORT_FROM              8 (SessionPasswordNeededError)
             44 STORE_NAME               8 (SessionPasswordNeededError)
             46 POP_TOP

  4          48 LOAD_CONST               0 (0)
             50 LOAD_CONST               4 (('sleep',))
             52 IMPORT_NAME              9 (time)
             54 IMPORT_FROM             10 (sleep)
             56 STORE_NAME              10 (sleep)
             58 POP_TOP

  5          60 LOAD_CONST               0 (0)
             62 LOAD_CONST               5 (('BeautifulSoup',))
             64 IMPORT_NAME             11 (bs4)
             66 IMPORT_FROM             12 (BeautifulSoup)
             68 STORE_NAME              12 (BeautifulSoup)
             70 POP_TOP

  6          72 LOAD_CONST               0 (0)
             74 LOAD_CONST               6 (None)
             76 IMPORT_NAME             13 (re)
             78 STORE_NAME              13 (re)
             80 LOAD_CONST               0 (0)
             82 LOAD_CONST               6 (None)
             84 IMPORT_NAME             14 (sys)
             86 STORE_NAME              14 (sys)
             88 LOAD_CONST               0 (0)
             90 LOAD_CONST               6 (None)
             92 IMPORT_NAME             15 (os)
             94 STORE_NAME              15 (os)
             96 LOAD_CONST               0 (0)
             98 LOAD_CONST               6 (None)
            100 IMPORT_NAME              9 (time)
            102 STORE_NAME               9 (time)
            104 LOAD_CONST               0 (0)
            106 LOAD_CONST               6 (None)
            108 IMPORT_NAME             16 (colorama)
            110 STORE_NAME              16 (colorama)
            112 LOAD_CONST               0 (0)
            114 LOAD_CONST               6 (None)
            116 IMPORT_NAME             17 (random)
            118 STORE_NAME              17 (random)
            120 LOAD_CONST               0 (0)
            122 LOAD_CONST               6 (None)
            124 IMPORT_NAME             18 (json)
            126 STORE_NAME              18 (json)
            128 LOAD_CONST               0 (0)
            130 LOAD_CONST               6 (None)
            132 IMPORT_NAME             19 (threading)
            134 STORE_NAME              19 (threading)
            136 LOAD_CONST               0 (0)
            138 LOAD_CONST               6 (None)
            140 IMPORT_NAME             20 (itertools)
            142 STORE_NAME              20 (itertools)
            144 LOAD_CONST               0 (0)
            146 LOAD_CONST               6 (None)
            148 IMPORT_NAME             21 (requests)
            150 STORE_NAME              21 (requests)

  7         152 LOAD_NAME               22 (open)
            154 LOAD_CONST               7 ('cfg.json')
            156 LOAD_CONST               8 ('r')
            158 CALL_FUNCTION            2
            160 SETUP_WITH              64 (to 226)
            162 STORE_NAME              23 (fh)

  8         164 LOAD_NAME               23 (fh)
            166 LOAD_METHOD             24 (read)
            168 CALL_METHOD              0
            170 STORE_NAME              25 (json_str)

  9         172 LOAD_NAME               18 (json)
            174 LOAD_METHOD             26 (loads)
            176 LOAD_NAME               25 (json_str)
            178 CALL_METHOD              1
            180 STORE_NAME              27 (json_value)

 10         182 LOAD_NAME               27 (json_value)
            184 LOAD_CONST               9 ('walletltc')
            186 BINARY_SUBSCR
            188 STORE_NAME              28 (ltcwallet)

 11         190 LOAD_NAME               27 (json_value)
            192 LOAD_CONST              10 ('walletdoge')
            194 BINARY_SUBSCR
            196 STORE_NAME              29 (dogewallet)

 12         198 LOAD_NAME               27 (json_value)
            200 LOAD_CONST              11 ('walletzec')
            202 BINARY_SUBSCR
            204 STORE_NAME              30 (zecwallet)

 13         206 LOAD_NAME               27 (json_value)
            208 LOAD_CONST              12 ('walletbch')
            210 BINARY_SUBSCR
            212 STORE_NAME              31 (bchwallet)

 14         214 LOAD_NAME               27 (json_value)
            216 LOAD_CONST              13 ('walletbtc')
            218 BINARY_SUBSCR
            220 STORE_NAME              32 (btcwallet)
            222 POP_BLOCK
            224 BEGIN_FINALLY
        >>  226 WITH_CLEANUP_START
            228 WITH_CLEANUP_FINISH
            230 END_FINALLY
from telethon import TelegramClient, sync, events
from telethon.tl.functions.messages import GetHistoryRequest, GetBotCallbackAnswerRequest
from telethon.errors import SessionPasswordNeededError
from time import sleep
from bs4 import BeautifulSoup
import re, sys, os, time, colorama, random, json, threading, itertools, requests
with open('cfg.json', 'r') as fh:
    json_str = fh.read()
    json_value = json.loads(json_str)
    ltcwallet = json_value['walletltc']
    dogewallet = json_value['walletdoge']
    zecwallet = json_value['walletzec']
    bchwallet = json_value['walletbch']
    btcwallet = json_value['walletbtc']

 16         232 LOAD_CONST              14 (<code object mengetik at 0xae3a56a0, file "<zen_ezz>", line 16>)
            234 LOAD_CONST              15 ('mengetik')
            236 MAKE_FUNCTION            0
            238 STORE_NAME              33 (mengetik)
def mengetik():

 22         240 LOAD_CONST              16 (<code object tunggu at 0xae5a7df0, file "<zen_ezz>", line 22>)
            242 LOAD_CONST              17 ('tunggu')
            244 MAKE_FUNCTION            0
            246 STORE_NAME              34 (tunggu)
def tunggu():

 32         248 LOAD_CONST              18 ('\x1b[1;35m\n                                              \neeeee  eeeee e    e eeee eeeee       e  eeeee \n8   8  8   8 8    8 8    "   8       8  8   8 \n8eee8e 8eee8 8eeee8 8eee eeee8       8e 8e  8 \n88   8 88  8   88   88   88          88 88  8 \n88   8 88  8   88   88ee 88ee8       88 88ee8 \n                               eeeee\n\x1b[1;36m=============================================\n\x1b[1;32m ~ anthesphong1998@gmail.com - t.me/rayez_id   \n\x1b[1;36m=============================================\n')
            250 STORE_NAME              35 (banner)

 44         252 LOAD_NAME               15 (os)
            254 LOAD_METHOD             36 (system)
            256 LOAD_CONST              19 ('clear')
            258 CALL_METHOD              1
            260 POP_TOP

 45         262 LOAD_NAME               37 (print)
            264 LOAD_NAME               35 (banner)
            266 CALL_FUNCTION            1
            268 POP_TOP

 46         270 LOAD_NAME               37 (print)
            272 LOAD_CONST              20 ('\x1b[1;35mCONFIGURATION SETTING \x1b[1;36m: AUTO VISIT & WD CLICKBOT')
            274 CALL_FUNCTION            1
            276 POP_TOP
banner = '\x1b[1;35m\n                                              \neeeee  eeeee e    e eeee eeeee       e  eeeee \n8   8  8   8 8    8 8    "   8       8  8   8 \n8eee8e 8eee8 8eeee8 8eee eeee8       8e 8e  8 \n88   8 88  8   88   88   88          88 88  8 \n88   8 88  8   88   88ee 88ee8       88 88ee8 \n                               eeeee\n\x1b[1;36m=============================================\n\x1b[1;32m ~ anthesphong1998@gmail.com - t.me/rayez_id   \n\x1b[1;36m=============================================\n'
os.system('clear')
print(banner)
print('\x1b[1;35mCONFIGURATION SETTING \x1b[1;36m: AUTO VISIT & WD CLICKBOT')

 48         278 LOAD_CONST              21 (<code object password at 0xae33b708, file "<zen_ezz>", line 48>)
            280 LOAD_CONST              22 ('password')
            282 MAKE_FUNCTION            0
            284 STORE_NAME              38 (password)
def password():

 71         286 LOAD_NAME               38 (password)
            288 CALL_FUNCTION            0
            290 POP_TOP
password()

 72         292 LOAD_NAME               39 (input)
            294 LOAD_CONST              23 ('\x1b[1;35mINPUT CURRENCY        \x1b[1;36m: ')
            296 CALL_FUNCTION            1
            298 STORE_NAME              40 (currency)

 73         300 LOAD_NAME               40 (currency)
            302 LOAD_CONST              24 ('doge')
            304 COMPARE_OP               2 (==)
            306 EXTENDED_ARG             1
            308 POP_JUMP_IF_TRUE       350
            310 LOAD_NAME               40 (currency)
            312 LOAD_CONST              25 ('ltc')
            314 COMPARE_OP               2 (==)
            316 EXTENDED_ARG             1
            318 POP_JUMP_IF_TRUE       350
            320 LOAD_NAME               40 (currency)
            322 LOAD_CONST              26 ('zec')
            324 COMPARE_OP               2 (==)
            326 EXTENDED_ARG             1
            328 POP_JUMP_IF_TRUE       350
            330 LOAD_NAME               40 (currency)
            332 LOAD_CONST              27 ('btc')
            334 COMPARE_OP               2 (==)
            336 EXTENDED_ARG             1
            338 POP_JUMP_IF_TRUE       350
            340 LOAD_NAME               40 (currency)
            342 LOAD_CONST              28 ('bch')
            344 COMPARE_OP               2 (==)
            346 EXTENDED_ARG             1
            348 POP_JUMP_IF_FALSE      360

 74     >>  350 LOAD_NAME               37 (print)
            352 LOAD_CONST              29 ('\n\n\n\n\n\n\n\n\n\n\n\n\n\n\n\n\n\n\n\n\n\n\n\n\n\n\n\n\n\n\n\n\n\n\n\n\n\n\n\n\n\n\n\n\n\n\n\n\n\n\n\n\n\n\n\n\n\n\n\n')
            354 CALL_FUNCTION            1
            356 POP_TOP
            358 JUMP_FORWARD            16 (to 376)

 76     >>  360 LOAD_NAME               37 (print)
            362 LOAD_CONST              30 ('\x1b[1;35mSTATUS                \x1b[1;36m: Wrong Input \n')
            364 CALL_FUNCTION            1
            366 POP_TOP

 77         368 LOAD_NAME               14 (sys)
            370 LOAD_METHOD             41 (exit)
            372 CALL_METHOD              0
            374 POP_TOP

 78     >>  376 LOAD_NAME               37 (print)
            378 LOAD_NAME               16 (colorama)
            380 LOAD_ATTR               42 (ansi)
            382 LOAD_METHOD             43 (clear_screen)
            384 CALL_METHOD              0
            386 CALL_FUNCTION            1
            388 POP_TOP

 79         390 LOAD_CONST              31 (False)
            392 STORE_NAME              44 (done)
currency = input('\x1b[1;35mINPUT CURRENCY        \x1b[1;36m: ')
if currency == 'doge' or currency == 'ltc' or currency == 'zec' or currency == 'btc' or currency == 'bch':
    print('\n\n\n\n\n\n\n\n\n\n\n\n\n\n\n\n\n\n\n\n\n\n\n\n\n\n\n\n\n\n\n\n\n\n\n\n\n\n\n\n\n\n\n\n\n\n\n\n\n\n\n\n\n\n\n\n\n\n\n\n')
else:
    print('\x1b[1;35mSTATUS                \x1b[1;36m: Wrong Input \n')
    sys.exit()
print(colorama.ansi.clear_screen())
done = False

 81         394 LOAD_CONST              32 (<code object animate at 0xae33b840, file "<zen_ezz>", line 81>)
            396 LOAD_CONST              33 ('animate')
            398 MAKE_FUNCTION            0
            400 STORE_NAME              45 (animate)
def animate():

 89         402 LOAD_NAME               19 (threading)
            404 LOAD_ATTR               46 (Thread)
            406 LOAD_NAME               45 (animate)
            408 LOAD_CONST              34 (('target',))
            410 CALL_FUNCTION_KW         1
            412 STORE_NAME              47 (t)

 90         414 LOAD_NAME               47 (t)
            416 LOAD_METHOD             48 (start)
            418 CALL_METHOD              0
            420 POP_TOP

 91         422 LOAD_NAME                9 (time)
            424 LOAD_METHOD             10 (sleep)
            426 LOAD_CONST              35 (2)
            428 CALL_METHOD              1
            430 POP_TOP

 92         432 LOAD_CONST              36 (True)
            434 STORE_NAME              44 (done)

 94         436 LOAD_CONST              37 (' Jangan lupa bahagia, tersenyumlah =)')

 93         438 BUILD_LIST               1
            440 STORE_NAME              49 (lines)

 95         442 LOAD_NAME               49 (lines)
            444 GET_ITER
        >>  446 FOR_ITER                66 (to 514)
            448 STORE_NAME              50 (line)

 96         450 LOAD_NAME               50 (line)
            452 GET_ITER
        >>  454 FOR_ITER                38 (to 494)
            456 STORE_NAME              51 (c)

 97         458 LOAD_NAME               37 (print)
            460 LOAD_NAME               51 (c)
            462 LOAD_CONST              38 ('')
            464 LOAD_CONST              39 (('end',))
            466 CALL_FUNCTION_KW         2
            468 POP_TOP

 98         470 LOAD_NAME               14 (sys)
            472 LOAD_ATTR               52 (stdout)
            474 LOAD_METHOD             53 (flush)
            476 CALL_METHOD              0
            478 POP_TOP

 99         480 LOAD_NAME                9 (time)
            482 LOAD_METHOD             10 (sleep)
            484 LOAD_CONST              40 (0.1)
            486 CALL_METHOD              1
            488 POP_TOP
            490 EXTENDED_ARG             1
            492 JUMP_ABSOLUTE          454
t = threading.Thread(target=animate)
t.start()
time.sleep(2)
done = True
lines = [
 ' Jangan lupa bahagia, tersenyumlah =)']
for line in lines:
    for c in line:
        print(c, end='')
        sys.stdout.flush()
        time.sleep(0.1)

100     >>  494 LOAD_NAME               37 (print)
            496 LOAD_CONST              41 ('\n')
            498 CALL_FUNCTION            1
            500 POP_TOP

101         502 LOAD_NAME               10 (sleep)
            504 LOAD_CONST              35 (2)
            506 CALL_FUNCTION            1
            508 POP_TOP
            510 EXTENDED_ARG             1
            512 JUMP_ABSOLUTE          446
print('\n')
sleep(2)

103     >>  514 LOAD_NAME               15 (os)
            516 LOAD_ATTR               54 (path)
            518 LOAD_METHOD             55 (exists)
            520 LOAD_CONST              42 ('session')
            522 CALL_METHOD              1
            524 EXTENDED_ARG             2
            526 POP_JUMP_IF_TRUE       538

104         528 LOAD_NAME               15 (os)
            530 LOAD_METHOD             56 (makedirs)
            532 LOAD_CONST              42 ('session')
            534 CALL_METHOD              1
            536 POP_TOP

106     >>  538 LOAD_NAME               15 (os)
            540 LOAD_METHOD             36 (system)
            542 LOAD_CONST              19 ('clear')
            544 CALL_METHOD              1
            546 POP_TOP

107         548 LOAD_NAME               21 (requests)
            550 LOAD_METHOD             57 (get)
            552 LOAD_CONST              43 ('https://ipinfo.io/json')
            554 CALL_METHOD              1
            556 STORE_NAME              58 (r)

108         558 LOAD_NAME               18 (json)
            560 LOAD_METHOD             26 (loads)
            562 LOAD_NAME               58 (r)
            564 LOAD_ATTR               59 (text)
            566 CALL_METHOD              1
            568 STORE_NAME              60 (data)

109         570 LOAD_CONST              44 ('\x1b[1;35mYOUR LOCATION\t: \x1b[1;36m{1}\t({2})\n\x1b[1;35mYOUR OWN IP\t: \x1b[1;36m{0}')
            572 STORE_NAME              59 (text)

110         574 LOAD_NAME               59 (text)
            576 LOAD_METHOD             61 (format)
            578 LOAD_NAME               60 (data)
            580 LOAD_METHOD             57 (get)
            582 LOAD_CONST              45 ('ip')
            584 LOAD_CONST              46 ('[NO DATA]')
            586 CALL_METHOD              2
            588 LOAD_NAME               60 (data)
            590 LOAD_METHOD             57 (get)
            592 LOAD_CONST              47 ('region')
            594 LOAD_CONST              46 ('[NO DATA]')
            596 CALL_METHOD              2
            598 LOAD_NAME               60 (data)
            600 LOAD_METHOD             57 (get)
            602 LOAD_CONST              48 ('country')
            604 LOAD_CONST              46 ('[NO DATA]')
            606 CALL_METHOD              2
            608 CALL_METHOD              3
            610 STORE_NAME              59 (text)

111         612 LOAD_NAME               37 (print)
            614 LOAD_NAME               35 (banner)
            616 CALL_FUNCTION            1
            618 POP_TOP

112         620 LOAD_NAME               33 (mengetik)
            622 LOAD_NAME               59 (text)
            624 CALL_FUNCTION            1
            626 POP_TOP

113         628 LOAD_NAME               33 (mengetik)
            630 LOAD_CONST              49 ('\x1b[1;35mWELCOME TO BOT  :\x1b[1;36m Visit and Withdraw Clickbot\n\x1b[1;35mNOTE            :\x1b[1;36m This Script Is not for sale !\n')
            632 CALL_FUNCTION            1
            634 POP_TOP

114         636 LOAD_CONST              50 ('User-Agent')
            638 LOAD_CONST              51 ('Mozilla/5.0 (Windows NT 10.0; Win32; x86) AppleWebKit/537.36 (KHTML, like Gecko) Chrome/67.0.3396.99 Safari/537.36')
            640 BUILD_MAP                1
            642 STORE_NAME              62 (ua)

115         644 LOAD_CONST              52 (800812)
            646 STORE_NAME              63 (api_id)

116         648 LOAD_CONST              53 ('db55ad67a98df35667ca788b97f771f5')
            650 STORE_NAME              64 (api_hash)
os.path.exists('session') or os.makedirs('session')
os.system('clear')
r = requests.get('https://ipinfo.io/json')
data = json.loads(r.text)
text = '\x1b[1;35mYOUR LOCATION\t: \x1b[1;36m{1}\t({2})\n\x1b[1;35mYOUR OWN IP\t: \x1b[1;36m{0}'
text = text.format(data.get('ip', '[NO DATA]'), data.get('region', '[NO DATA]'), data.get('country', '[NO DATA]'))
print(banner)
mengetik(text)
mengetik('\x1b[1;35mWELCOME TO BOT  :\x1b[1;36m Visit and Withdraw Clickbot\n\x1b[1;35mNOTE            :\x1b[1;36m This Script Is not for sale !\n')
ua = {'User-Agent': 'Mozilla/5.0 (Windows NT 10.0; Win32; x86) AppleWebKit/537.36 (KHTML, like Gecko) Chrome/67.0.3396.99 Safari/537.36'}
api_id = 800812
api_hash = 'db55ad67a98df35667ca788b97f771f5'

118         652 LOAD_CONST              54 (<code object withdraw at 0xae33b8a8, file "<zen_ezz>", line 118>)
            654 LOAD_CONST              55 ('withdraw')
            656 MAKE_FUNCTION            0
            658 STORE_NAME              65 (withdraw)
def withdraw():

144         660 LOAD_CONST              56 (<code object visit at 0xae33b910, file "<zen_ezz>", line 144>)
            662 LOAD_CONST              57 ('visit')
            664 MAKE_FUNCTION            0
            666 STORE_NAME              66 (visit)
def visit():

221         668 LOAD_NAME               22 (open)
            670 LOAD_CONST              58 ('list.txt')
            672 CALL_FUNCTION            1
            674 STORE_NAME              67 (f)

222         676 LOAD_NAME               68 (len)
            678 LOAD_NAME               67 (f)
            680 LOAD_METHOD             69 (readlines)
            682 CALL_METHOD              0
            684 CALL_FUNCTION            1
            686 STORE_NAME              70 (baris)

223         688 LOAD_NAME               67 (f)
            690 LOAD_METHOD             71 (close)
            692 CALL_METHOD              0
            694 POP_TOP

225         696 LOAD_NAME               72 (range)
            698 LOAD_NAME               70 (baris)
            700 CALL_FUNCTION            1
            702 GET_ITER
        >>  704 EXTENDED_ARG             1
            706 FOR_ITER               460 (to 1168)
            708 STORE_NAME              73 (i)
	
226         710 LOAD_NAME               22 (open)
            712 LOAD_CONST              58 ('list.txt')
            714 CALL_FUNCTION            1
            716 STORE_NAME              67 (f)

227         718 LOAD_NAME               67 (f)
            720 LOAD_METHOD             69 (readlines)
            722 CALL_METHOD              0
            724 LOAD_NAME               73 (i)
            726 BINARY_SUBSCR
            728 LOAD_METHOD             74 (strip)
            730 CALL_METHOD              0
            732 STORE_NAME              75 (phone_number)

228         734 LOAD_NAME               67 (f)
            736 LOAD_METHOD             71 (close)
            738 CALL_METHOD              0
            740 POP_TOP
f = open('list.txt')
baris = len(f.readlines())
f.close()
for i in range(baris):
    f = open('list.txt')
    phone_number = f.readlines()[i].strip()
    f.close()

229         742 LOAD_NAME               33 (mengetik)
            744 LOAD_CONST              59 ('\x1b[1;36m===============================================\n')
            746 CALL_FUNCTION            1
            748 POP_TOP

230         750 LOAD_NAME               37 (print)
            752 LOAD_CONST              60 ('\x1b[1;35mYOUR NUMBER     : \x1b[1;36m')
            754 LOAD_NAME               75 (phone_number)
            756 FORMAT_VALUE             0
            758 BUILD_STRING             2
            760 CALL_FUNCTION            1
            762 POP_TOP

231         764 LOAD_NAME                1 (TelegramClient)
            766 LOAD_CONST              61 ('session/')
            768 LOAD_NAME               75 (phone_number)
            770 BINARY_ADD
            772 LOAD_NAME               63 (api_id)
            774 LOAD_NAME               64 (api_hash)
            776 CALL_FUNCTION            3
            778 STORE_NAME              76 (client)

232         780 LOAD_NAME               76 (client)
            782 LOAD_METHOD             77 (connect)
            784 CALL_METHOD              0
            786 POP_TOP

233         788 LOAD_NAME               76 (client)
            790 LOAD_METHOD             78 (is_user_authorized)
            792 CALL_METHOD              0
            794 EXTENDED_ARG             3
            796 POP_JUMP_IF_TRUE       912
mengetik('\x1b[1;36m===============================================\n')
print(f"\x1b[1;35mYOUR NUMBER     : \x1b[1;36m{phone_number}")
client = TelegramClient('session/' + phone_number, api_id, api_hash)
client.connect()
client.is_user_authorized()

234         798 SETUP_FINALLY           30 (to 830)
try:

235         800 LOAD_NAME               76 (client)
            802 LOAD_METHOD             79 (send_code_request)
            804 LOAD_NAME               75 (phone_number)
            806 CALL_METHOD              1
            808 POP_TOP

236         810 LOAD_NAME               76 (client)
            812 LOAD_METHOD             80 (sign_in)
            814 LOAD_NAME               75 (phone_number)
            816 LOAD_NAME               39 (input)
            818 LOAD_CONST              62 ('\x1b[1;35mVERIF CODE      : \x1b[1;36m')
            820 CALL_FUNCTION            1
            822 CALL_METHOD              2
            824 STORE_NAME              81 (me)
            826 POP_BLOCK
            828 JUMP_FORWARD            82 (to 912)
client.send_code_request(phone_number)
me = client.sign_in(phone_number, input('\x1b[1;35mVERIF CODE      : \x1b[1;36m'))

237     >>  830 DUP_TOP
            832 LOAD_NAME                8 (SessionPasswordNeededError)
            834 COMPARE_OP              10 (exception match)
            836 EXTENDED_ARG             3
            838 POP_JUMP_IF_FALSE      870
            840 POP_TOP
            842 POP_TOP
            844 POP_TOP

238         846 LOAD_NAME               39 (input)
            848 LOAD_CONST              63 ('\x1b[1;35m2FA CODE        : \x1b[1;36m')
            850 CALL_FUNCTION            1
            852 STORE_NAME              82 (passw)

239         854 LOAD_NAME               76 (client)
            856 LOAD_METHOD             48 (start)
            858 LOAD_NAME               75 (phone_number)
            860 LOAD_NAME               82 (passw)
            862 CALL_METHOD              2
            864 STORE_NAME              81 (me)
            866 POP_EXCEPT
            868 JUMP_FORWARD            42 (to 912)
except (SessionPasswordNeededError):
	passw = input('\x1b[1;35m2FA CODE        : \x1b[1;36m')
	me = client.start(phone_number, passw)
	
240     >>  870 DUP_TOP
            872 LOAD_NAME               83 (Exception)
            874 COMPARE_OP              10 (exception match)
            876 EXTENDED_ARG             3
            878 POP_JUMP_IF_FALSE      910
            880 POP_TOP
            882 POP_TOP
            884 POP_TOP
except Exception:

241         886 LOAD_NAME               14 (sys)
            888 LOAD_ATTR               52 (stdout)
            890 LOAD_METHOD             84 (write)
            892 LOAD_CONST              64 ('\r\x1b[1;35mSTATUS          : \x1b[1;36mSomething Wrong happened !\n')
            894 CALL_METHOD              1
            896 POP_TOP
sys.stdout.write('\r\x1b[1;35mSTATUS          : \x1b[1;36mSomething Wrong happened !\n')

242         898 POP_EXCEPT
            900 POP_TOP
            902 EXTENDED_ARG             4
            904 JUMP_ABSOLUTE         1168
            906 POP_EXCEPT
            908 JUMP_FORWARD             2 (to 912)
        >>  910 END_FINALLY

243     >>  912 LOAD_NAME               76 (client)
            914 LOAD_METHOD             85 (get_me)
            916 CALL_METHOD              0
            918 STORE_NAME              86 (myself)
myself = client.get_me()

244         920 SETUP_FINALLY          232 (to 1154)
            922 SETUP_FINALLY          184 (to 1108)
try:

245         924 LOAD_NAME               40 (currency)
            926 LOAD_CONST              24 ('doge')
            928 COMPARE_OP               2 (==)
            930 EXTENDED_ARG             3
            932 POP_JUMP_IF_FALSE      958

246         934 LOAD_NAME               76 (client)
            936 LOAD_METHOD             88 (get_entity)
            938 LOAD_CONST              65 ('@Dogecoin_click_bot')
            940 CALL_METHOD              1
            942 STORE_NAME              89 (channel_entity)

247         944 LOAD_CONST              65 ('@Dogecoin_click_bot')
            946 STORE_NAME              90 (channel_username)

248         948 LOAD_CONST              66 ('DOGE')
            950 STORE_NAME              91 (cr)

249         952 LOAD_NAME               29 (dogewallet)
            954 STORE_NAME              92 (wallet)
            956 JUMP_FORWARD           134 (to 1092)
if currency == 'doge':
	channel_entity = client.get_entity('@Dogecoin_click_bot')
	channel_username = '@Dogecoin_click_bot'
	cr = 'DOGE'
	wallet = dogewallet

250     >>  958 LOAD_NAME               40 (currency)
            960 LOAD_CONST              25 ('ltc')
            962 COMPARE_OP               2 (==)
            964 EXTENDED_ARG             3
            966 POP_JUMP_IF_FALSE      992

251         968 LOAD_NAME               76 (client)
            970 LOAD_METHOD             88 (get_entity)
            972 LOAD_CONST              67 ('@Litecoin_click_bot')
            974 CALL_METHOD              1
            976 STORE_NAME              89 (channel_entity)

252         978 LOAD_CONST              67 ('@Litecoin_click_bot')
            980 STORE_NAME              90 (channel_username)

253         982 LOAD_CONST              68 ('LTC')
            984 STORE_NAME              91 (cr)

254         986 LOAD_NAME               28 (ltcwallet)
            988 STORE_NAME              92 (wallet)
            990 JUMP_FORWARD           100 (to 1092)
elif currency == 'ltc':
	channel_entity = client.get_entity('@Litecoin_click_bot')
	channel_username = '@Litecoin_click_bot'
	cr = 'LTC'
	wallet = ltcwallet

255     >>  992 LOAD_NAME               40 (currency)
            994 LOAD_CONST              26 ('zec')
            996 COMPARE_OP               2 (==)
            998 EXTENDED_ARG             4
           1000 POP_JUMP_IF_FALSE     1026

256        1002 LOAD_NAME               76 (client)
           1004 LOAD_METHOD             88 (get_entity)
           1006 LOAD_CONST              69 ('@Zcash_click_bot')
           1008 CALL_METHOD              1
           1010 STORE_NAME              89 (channel_entity)

257        1012 LOAD_CONST              69 ('@Zcash_click_bot')
           1014 STORE_NAME              90 (channel_username)

258        1016 LOAD_CONST              70 ('ZEC')
           1018 STORE_NAME              91 (cr)

259        1020 LOAD_NAME               30 (zecwallet)
           1022 STORE_NAME              92 (wallet)
           1024 JUMP_FORWARD            66 (to 1092)
elif currency == 'zec':
	channel_entity = client.get_entity('@Zcash_click_bot')
	channel_username = '@Zcash_click_bot'
	cr = 'ZEC'
	wallet = zecwallet

260     >> 1026 LOAD_NAME               40 (currency)
           1028 LOAD_CONST              28 ('bch')
           1030 COMPARE_OP               2 (==)
           1032 EXTENDED_ARG             4
           1034 POP_JUMP_IF_FALSE     1060

261        1036 LOAD_NAME               76 (client)
           1038 LOAD_METHOD             88 (get_entity)
           1040 LOAD_CONST              71 ('@BCH_clickbot')
           1042 CALL_METHOD              1
           1044 STORE_NAME              89 (channel_entity)

262        1046 LOAD_CONST              71 ('@BCH_clickbot')
           1048 STORE_NAME              90 (channel_username)

263        1050 LOAD_CONST              72 ('BCH')
           1052 STORE_NAME              91 (cr)

264        1054 LOAD_NAME               31 (bchwallet)
           1056 STORE_NAME              92 (wallet)
           1058 JUMP_FORWARD            32 (to 1092)
elif currency == 'bch':
	channel_entity = client.get_entity('@BCH_clickbot')
	channel_username = '@BCH_clickbot'
	cr = 'BCH'
	wallet = bchwallet

265     >> 1060 LOAD_NAME               40 (currency)
           1062 LOAD_CONST              27 ('btc')
           1064 COMPARE_OP               2 (==)
           1066 EXTENDED_ARG             4
           1068 POP_JUMP_IF_FALSE     1092

266        1070 LOAD_NAME               76 (client)
           1072 LOAD_METHOD             88 (get_entity)
           1074 LOAD_CONST              73 ('@BitcoinClick_bot')
           1076 CALL_METHOD              1
           1078 STORE_NAME              89 (channel_entity)

267        1080 LOAD_CONST              73 ('@BitcoinClick_bot')
           1082 STORE_NAME              90 (channel_username)

268        1084 LOAD_CONST              74 ('BTC')
           1086 STORE_NAME              91 (cr)

269        1088 LOAD_NAME               32 (btcwallet)
           1090 STORE_NAME              92 (wallet)
elif currency == 'btc':
	channel_entity = client.get_entity('@BitcoinClick_bot')
	channel_username = '@BitcoinClick_bot'
	cr = 'BTC'
	wallet = btcwallet

270     >> 1092 LOAD_NAME               66 (visit)
           1094 CALL_FUNCTION            0
           1096 POP_TOP
visit()

271        1098 LOAD_NAME               65 (withdraw)
           1100 CALL_FUNCTION            0
           1102 POP_TOP
           1104 POP_BLOCK
           1106 JUMP_FORWARD            42 (to 1150)
withdraw()

272     >> 1108 DUP_TOP
           1110 LOAD_NAME               83 (Exception)
           1112 COMPARE_OP              10 (exception match)
           1114 EXTENDED_ARG             4
           1116 POP_JUMP_IF_FALSE     1148
           1118 POP_TOP
           1120 POP_TOP
           1122 POP_TOP

273        1124 LOAD_NAME               14 (sys)
           1126 LOAD_ATTR               52 (stdout)
           1128 LOAD_METHOD             84 (write)
           1130 LOAD_CONST              75 ('\r\x1b[1;35mSTATUS AKUN     : \x1b[1;36mSomething Wrong happened !\n\n')
           1132 CALL_METHOD              1
           1134 POP_TOP

274        1136 LOAD_NAME               10 (sleep)
           1138 LOAD_CONST              76 (1)
           1140 CALL_FUNCTION            1
           1142 POP_TOP
           1144 POP_EXCEPT
           1146 JUMP_FORWARD             2 (to 1150)
        >> 1148 END_FINALLY
        >> 1150 POP_BLOCK
           1152 BEGIN_FINALLY
else:
	pass
276     >> 1154 LOAD_NAME               76 (client)
           1156 LOAD_METHOD             87 (disconnect)
           1158 CALL_METHOD              0
           1160 POP_TOP
           1162 END_FINALLY # <- pass? 
           1164 EXTENDED_ARG             2
           1166 JUMP_ABSOLUTE          704
        >> 1168 LOAD_CONST               6 (None)
           1170 RETURN_VALUE
except Exception:
	sys.stdout.write('\r\x1b[1;35mSTATUS AKUN     : \x1b[1;36mSomething Wrong happened !\n\n')
	sleep(1)
	client.disconnect()
