# FileNames : pycompyle.py
# Python Bytecode : 2.7.18
# Selector <module> In Line 1 file pycompyle.pyc
# Timestamp In Code :  (2020-09-05 20:10:01)

# Method Name:       <module>
# Filename:          pycompyle.py
# Argument count:    0
# Number of locals:  0
# Stack size:        6
# Flags:             0x00000040 (NOFREE)
# First Line:        1
# Constants:
#    0: 0
#    1: -1
#    2: None
#    3: 'utf-8'
#    4: '1.0.0'
#    5: '2020/09/02'
#    6: 'PyCompyle\n\tScript to make pyc anti-decompiler.\nUsage : python2 -m pycompyle file'
#    7: <code object <lambda> at 0xa9b4e9b0, file "pycompyle.py", line 18>
#    8: <code object __comb_open at 0xa9b4e848, file "pycompyle.py", line 22>
#    9: <code object __comb_exists at 0xa9b5a770, file "pycompyle.py", line 27>
#   10: '.SELF/'
#   11: '\\eJzjUlZIzS0oqVRIy8xJ5QIAHdMERw=='
#   12: '.SELF/pycompyle/__init__.py'
#   13: 'pycompyle'
#   14: '\\eJzFlOtv4kYQwP91J9V5YxGtm+NyTbk8Kh5ClcmHU9RIyZWrvSbGeAOmYY0VYpucgUDcw4jkUhlI\nQtfgXEiPfu1J/jCzO955/Wb2h0RB3WAoJGCVKbc1x8U4N06vVOSJak3BkJxcuLjhloZkv3hlSqMa\ndDXn6Vb2DLuloCdVCjjHqylP6qlHcD6eXpFxH0Qvp0yTSMUuAu/3oQDgI8FdZAdBuS1jGsC1Yvsb\niYyMe6rmk8aoIn7mufvC1aX+rmAkemvisXdRsm23fN4bnHwyH0p6Im8oB3bz+HHrSH+XP0X5L1Yr\nvjVqltOvlY89qxu//t2YHia45MxdvyIOAs2r6f/lK/jzQTLfjv9yDurupBo/ZMAKoD9avom8Aiay\nPlXgYZQXM0Bh2EHNckulFGM/fGlPnKZvmuPPzn0inoNp6lEIhgTEBaxfnWgeqGeB+R5wOa7Qroip\n+3LLYNuGlmreuWMgjGAoO3epF8bsLYgJDnQlOBd+S8APAHcJFhyQ5ItZgPwSewNBHQJBkkagKFRE\nwdA7Ik5h3OHrSXg7z/2+0mgBaYLEpxasCswkB6FHYH9nFmr42e0zq4eGYU1o2BIzQvqAnxfh5RXN\ni78IEPKJTQrSgL52ogdo6w9O80PVnhrFjsi+zKWeaq7OwkaedjpQ4G0M3uzAG6B3ZNjTrZQTO3q9\nlQSvhCYbXq2tzFSa1PqvMXi8+fPBxvbx5k95CEIbIj0aZX9Gziy8UGifFPxCgzaXBKePFTStiCRg\neqo8qSCfX4g/BifOsE8PYzCH6n4hwiM6pNmpdsbUpzrzSS12+IjqjFwclfQrxEZmcPWrWWAit4Zv\na2ybMBOl0eJCQjqK7PPOTaBS7JPw7sMY/gK4jGn2IqjO3ZoiqA5t33Mw1dNvOqJmqhZ9PLWsvLm/\np9rVQAthm785g5w7H1UaPj8k8zEMhinG8kpaW+OSXLmlFnuIrS5l2J4jREKEeO6yv6utndPZyQIq\n76Sf5b0FeXtukxyDeQ3DT9NHRPEwMziTJ/xzX7JAfbaRmD6+CHR28SRA+JLfzYLdxcN7ozhFLN05\nGRFPA9kTiz0+8hWoFyM6lWFB6FT+i23rmgEZA3ty5CKo6aPasC2pAQoJ6VJjqdiRhwOl4UHamnCO\nlnrxSxpR1T7BUwrGAnWZ8HeW0PJ+fSe2dKuwXUW+lnUhhP9NxDYEL0fDFBRxAMKFcLO6/XEDCOvw\nlg+v0mszVbWEV+tZsHf049v85t7R7lYSLi3CAuRctLVS4aiqLs0iXF//75zGYFgfA0+wTqP6XiVa\ntvrOKR6CYgvSm28GZ6GG8x1u4OmZ1QHsAgk/CKThGY1Ihel/AONaaaA='
#   15: <code object <lambda> at 0xa9b5a800, file "pycompyle.py", line 59>
#   16: <code object <lambda> at 0xa9b5a848, file "pycompyle.py", line 59>
#   17: 1278621296
#   18: '.SELF/pycompyle/__main__.py'
#   19: 'pycompyle.__main__'
#   20: ('compile',)
#   21: <code object main at 0xa9b5a890, file "pycompyle.py", line 68>
#   22: '__main__'
# Names:
#    0: False
#    1: foo
#    2: bar
#    3: sys
#    4: reload
#    5: setdefaultencoding
#    6: base64
#    7: imp
#    8: os
#    9: StringIO
#   10: zlib
#   11: __all__
#   12: __version__
#   13: __date__
#   14: __doc__
#   15: __FILES
#   16: path
#   17: exists
#   18: __os_path_exists
#   19: open
#   20: __builtin_open
#   21: ___
#   22: decodestring
#   23: __b64d
#   24: decompress
#   25: __zlibd
#   26: __comb_open
#   27: __comb_exists
#   28: new_module
#   29: modules
#   30: __dict__
#   31: __main__
#   32: pycompyle.__main__
#   33: compile
#   34: None
#   35: main
#   36: __name__
#   37: exit
  1           0 LOAD_NAME                0 (False)
              3 STORE_NAME               1 (foo)

  2           6 LOAD_NAME                1 (foo)
              9 POP_JUMP_IF_FALSE       35

  3          12 LOAD_CONST               0 (0)
             15 LOAD_CONST               0 (0)
             18 BINARY_DIVIDE       
             19 STORE_NAME               2 (bar)

  4          22 MAKE_FUNCTION           21
             25 MAKE_FUNCTION            1
             28 BINARY_DIVIDE       
             29 STORE_NAME               2 (bar)
             32 JUMP_FORWARD             0 (to 35)

  6     >>   35 LOAD_CONST               1 (-1)
             38 LOAD_CONST               2 (None)
             41 IMPORT_NAME              3 (sys)
             44 STORE_NAME               3 (sys)

  7          47 LOAD_NAME                4 (reload)
             50 LOAD_NAME                3 (sys)
             53 CALL_FUNCTION            1
             56 POP_TOP             

  8          57 LOAD_NAME                3 (sys)
             60 LOAD_ATTR                5 (setdefaultencoding)
             63 LOAD_CONST               3 ('utf-8')
             66 CALL_FUNCTION            1
             69 POP_TOP             

  9          70 LOAD_CONST               1 (-1)
             73 LOAD_CONST               2 (None)
             76 IMPORT_NAME              6 (base64)
             79 STORE_NAME               6 (base64)
             82 LOAD_CONST               1 (-1)
             85 LOAD_CONST               2 (None)
             88 IMPORT_NAME              7 (imp)
             91 STORE_NAME               7 (imp)
             94 LOAD_CONST               1 (-1)
             97 LOAD_CONST               2 (None)
            100 IMPORT_NAME              8 (os)
            103 STORE_NAME               8 (os)
            106 LOAD_CONST               1 (-1)
            109 LOAD_CONST               2 (None)
            112 IMPORT_NAME              9 (StringIO)
            115 STORE_NAME               9 (StringIO)
            118 LOAD_CONST               1 (-1)
            121 LOAD_CONST               2 (None)
            124 IMPORT_NAME             10 (zlib)
            127 STORE_NAME              10 (zlib)

 11         130 BUILD_LIST               0
            133 STORE_NAME              11 (__all__)

 12         136 LOAD_CONST               4 ('1.0.0')
            139 STORE_NAME              12 (__version__)

 13         142 LOAD_CONST               5 ('2020/09/02')
            145 STORE_NAME              13 (__date__)

 14         148 LOAD_CONST               6 ('PyCompyle\n\tScript to make pyc anti-decompiler.\nUsage : python2 -m pycompyle file')
            151 STORE_NAME              14 (__doc__)

 15         154 BUILD_MAP                0
            157 STORE_NAME              15 (__FILES)

 16         160 LOAD_NAME                8 (os)
            163 LOAD_ATTR               16 (path)
            166 LOAD_ATTR               17 (exists)
            169 STORE_NAME              18 (__os_path_exists)

 17         172 LOAD_NAME               19 (open)
            175 STORE_NAME              20 (__builtin_open)
import sys
reload(sys)
sys.setdefaultencoding('utf-8')
import base64
import imp
import os
import StringIO
import zlib
__all__ = []
__version__ = '1.0.0'
__date__ = '2020/09/02'
__doc__ = 'PyCompyle\n\tScript to make pyc anti-decompiler.\nUsage : python2 -m pycompyle file'
__FILES = { }
__os_path_exists = os.path.exists
__builtin_open = open

 18         178 LOAD_CONST               7 (<code object <lambda> at 0xa9b4e9b0, file "pycompyle.py", line 18>)
            181 MAKE_FUNCTION            0
            184 STORE_NAME              21 (___)
('').join([ chr(ord(x[i]) ^ ord(y[(lambda x, y: x % y if x % y >= 0 else y)(i, len(y))])) for i in range(len(x)) ])

 19         187 LOAD_NAME                6 (base64)
            190 LOAD_ATTR               22 (decodestring)
            193 STORE_NAME              23 (__b64d)

 20         196 LOAD_NAME               10 (zlib)
            199 LOAD_ATTR               24 (decompress)
            202 STORE_NAME              25 (__zlibd)
__b64d = base64.decodestring
__zlibd = zlib.decompress

 22         205 LOAD_CONST               8 (<code object __comb_open at 0xa9b4e848, file "pycompyle.py", line 22>)
            208 MAKE_FUNCTION            0
            211 STORE_NAME              26 (__comb_open)
def __comb_open():
	if filename in __FILES:
	    return StringIO.StringIO(__FILES[filename])
	else:
	    return __builtin_open(filename, *args, **kwargs)
 
 27         214 LOAD_CONST               9 (<code object __comb_exists at 0xa9b5a770, file "pycompyle.py", line 27>)
            217 MAKE_FUNCTION            0
            220 STORE_NAME              27 (__comb_exists)
def __comb_exits():
	if filename in __FILES:
	    return True
	else:
	    return __os_path_exists(filename, *args, **kwargs)
 
 33         223 LOAD_NAME               26 (__comb_open)
            226 STORE_NAME              19 (open)

 34         229 LOAD_NAME               27 (__comb_exists)
            232 LOAD_NAME                8 (os)
            235 LOAD_ATTR               16 (path)
            238 STORE_ATTR              17 (exists)

 35         241 LOAD_CONST              10 ('.SELF/')
            244 BUILD_LIST               1
            247 LOAD_NAME                3 (sys)
            250 LOAD_ATTR               16 (path)
            253 LOAD_CONST               0 (0)
            256 LOAD_CONST               0 (0)
            259 STORE_SLICE+3       

 37         260 LOAD_NAME               25 (__zlibd)
            263 LOAD_NAME               23 (__b64d)
            266 LOAD_CONST              11 ('\\eJzjUlZIzS0oqVRIy8xJ5QIAHdMERw==')
            269 CALL_FUNCTION            1
            272 CALL_FUNCTION            1
            275 LOAD_NAME               15 (__FILES)
            278 LOAD_CONST              12 ('.SELF/pycompyle/__init__.py')
            281 STORE_SUBSCR        

 38         282 LOAD_NAME                7 (imp)
            285 LOAD_ATTR               28 (new_module)
            288 LOAD_CONST              13 ('pycompyle')
            291 CALL_FUNCTION            1
            294 LOAD_NAME                3 (sys)
            297 LOAD_ATTR               29 (modules)
            300 LOAD_CONST              13 ('pycompyle')
            303 STORE_SUBSCR        

 39         304 LOAD_NAME               26 (__comb_open)
            307 LOAD_NAME                3 (sys)
            310 LOAD_ATTR               29 (modules)
            313 LOAD_CONST              13 ('pycompyle')
            316 BINARY_SUBSCR       
            317 STORE_ATTR              19 (open)

 40         320 LOAD_NAME               15 (__FILES)
            323 LOAD_CONST              12 ('.SELF/pycompyle/__init__.py')
            326 BINARY_SUBSCR       
            327 LOAD_NAME                3 (sys)
            330 LOAD_ATTR               29 (modules)
            333 LOAD_CONST              13 ('pycompyle')
            336 BINARY_SUBSCR       
            337 LOAD_ATTR               30 (__dict__)
            340 DUP_TOP             
            341 EXEC_STMT           
open = __comb_open
os.path.exists = __comb_exists
sys.path[0:0] = ['.SELF/']
__FILES['.SELF/pycompyle/__init__.py'] = __zlibd(__b64d('\\eJzjUlZIzS0oqVRIy8xJ5QIAHdMERw=='))
sys.modules['pycompyle'] = imp.new_module('pycompyle')
sys.modules['pycompyle'].open = __comb_open
exec __FILES['.SELF/pycompyle/__init__.py'] in sys.modules['pycompyle'].__dict__

 42         342 LOAD_NAME               21 (___)
            345 LOAD_NAME               25 (__zlibd)
            348 LOAD_NAME               23 (__b64d)

 59         351 LOAD_CONST              14 ('\\eJzFlOtv4kYQwP91J9V5YxGtm+NyTbk8Kh5ClcmHU9RIyZWrvSbGeAOmYY0VYpucgUDcw4jkUhlI\nQtfgXEiPfu1J/jCzO955/Wb2h0RB3WAoJGCVKbc1x8U4N06vVOSJak3BkJxcuLjhloZkv3hlSqMa\ndDXn6Vb2DLuloCdVCjjHqylP6qlHcD6eXpFxH0Qvp0yTSMUuAu/3oQDgI8FdZAdBuS1jGsC1Yvsb\niYyMe6rmk8aoIn7mufvC1aX+rmAkemvisXdRsm23fN4bnHwyH0p6Im8oB3bz+HHrSH+XP0X5L1Yr\nvjVqltOvlY89qxu//t2YHia45MxdvyIOAs2r6f/lK/jzQTLfjv9yDurupBo/ZMAKoD9avom8Aiay\nPlXgYZQXM0Bh2EHNckulFGM/fGlPnKZvmuPPzn0inoNp6lEIhgTEBaxfnWgeqGeB+R5wOa7Qroip\n+3LLYNuGlmreuWMgjGAoO3epF8bsLYgJDnQlOBd+S8APAHcJFhyQ5ItZgPwSewNBHQJBkkagKFRE\nwdA7Ik5h3OHrSXg7z/2+0mgBaYLEpxasCswkB6FHYH9nFmr42e0zq4eGYU1o2BIzQvqAnxfh5RXN\ni78IEPKJTQrSgL52ogdo6w9O80PVnhrFjsi+zKWeaq7OwkaedjpQ4G0M3uzAG6B3ZNjTrZQTO3q9\nlQSvhCYbXq2tzFSa1PqvMXi8+fPBxvbx5k95CEIbIj0aZX9Gziy8UGifFPxCgzaXBKePFTStiCRg\neqo8qSCfX4g/BifOsE8PYzCH6n4hwiM6pNmpdsbUpzrzSS12+IjqjFwclfQrxEZmcPWrWWAit4Zv\na2ybMBOl0eJCQjqK7PPOTaBS7JPw7sMY/gK4jGn2IqjO3ZoiqA5t33Mw1dNvOqJmqhZ9PLWsvLm/\np9rVQAthm785g5w7H1UaPj8k8zEMhinG8kpaW+OSXLmlFnuIrS5l2J4jREKEeO6yv6utndPZyQIq\n76Sf5b0FeXtukxyDeQ3DT9NHRPEwMziTJ/xzX7JAfbaRmD6+CHR28SRA+JLfzYLdxcN7ozhFLN05\nGRFPA9kTiz0+8hWoFyM6lWFB6FT+i23rmgEZA3ty5CKo6aPasC2pAQoJ6VJjqdiRhwOl4UHamnCO\nlnrxSxpR1T7BUwrGAnWZ8HeW0PJ+fSe2dKuwXUW+lnUhhP9NxDYEL0fDFBRxAMKFcLO6/XEDCOvw\nlg+v0mszVbWEV+tZsHf049v85t7R7lYSLi3CAuRctLVS4aiqLs0iXF//75zGYFgfA0+wTqP6XiVa\ntvrOKR6CYgvSm28GZ6GG8x1u4OmZ1QHsAgk/CKThGY1Ihel/AONaaaA=')
            354 CALL_FUNCTION            1
            357 CALL_FUNCTION            1
            360 LOAD_NAME               23 (__b64d)
            363 LOAD_CONST              15 (<code object <lambda> at 0xa9b5a800, file "pycompyle.py", line 59>)
            366 MAKE_FUNCTION            0
            369 LOAD_CONST              16 (<code object <lambda> at 0xa9b5a848, file "pycompyle.py", line 59>)

return y and chr(y % 256) + x(x, y // 256) or ''

            372 MAKE_FUNCTION            0
            375 LOAD_CONST              17 (1278621296)
            378 CALL_FUNCTION            2
            381 CALL_FUNCTION            1
            384 CALL_FUNCTION            2
            387 LOAD_NAME               15 (__FILES)
            390 LOAD_CONST              18 ('.SELF/pycompyle/__main__.py')
            393 STORE_SUBSCR        

 61         394 LOAD_NAME                7 (imp)
            397 LOAD_ATTR               28 (new_module)
            400 LOAD_CONST              19 ('pycompyle.__main__')
            403 CALL_FUNCTION            1
            406 LOAD_NAME                3 (sys)
            409 LOAD_ATTR               29 (modules)
            412 LOAD_CONST              19 ('pycompyle.__main__')
            415 STORE_SUBSCR        

 62         416 LOAD_NAME               26 (__comb_open)
            419 LOAD_NAME                3 (sys)
            422 LOAD_ATTR               29 (modules)
            425 LOAD_CONST              19 ('pycompyle.__main__')
            428 BINARY_SUBSCR       
            429 STORE_ATTR              19 (open)

 63         432 LOAD_NAME                3 (sys)
            435 LOAD_ATTR               29 (modules)
            438 LOAD_CONST              19 ('pycompyle.__main__')
            441 BINARY_SUBSCR       
            442 LOAD_NAME                3 (sys)
            445 LOAD_ATTR               29 (modules)
            448 LOAD_CONST              13 ('pycompyle')
            451 BINARY_SUBSCR       
            452 STORE_ATTR              31 (__main__)

 64         455 LOAD_NAME               15 (__FILES)
            458 LOAD_CONST              18 ('.SELF/pycompyle/__main__.py')
            461 BINARY_SUBSCR       
            462 LOAD_NAME                3 (sys)
            465 LOAD_ATTR               29 (modules)
            468 LOAD_CONST              19 ('pycompyle.__main__')
            471 BINARY_SUBSCR       
            472 LOAD_ATTR               30 (__dict__)
            475 DUP_TOP             
            476 EXEC_STMT           

 66         477 LOAD_CONST               1 (-1)
            480 LOAD_CONST              20 (('compile',))
            483 IMPORT_NAME             32 (pycompyle.__main__)
            486 IMPORT_FROM             33 (compile)
            489 STORE_NAME              33 (compile)
            492 POP_TOP             
sys.modules['pycompyle.__main__'] = imp.new_module('pycompyle.__main__')
sys.modules['pycompyle.__main__'].open = __comb_open
sys.modules['pycompyle'].__main__ = sys.modules['pycompyle.__main__']
exec __FILES['.SELF/pycompyle/__main__.py'] in sys.modules['pycompyle.__main__'].__dict__
from pycompyle.__main__ import compile

 68         493 LOAD_CONST               2 (None)
            496 LOAD_CONST              21 (<code object main at 0xa9b5a890, file "pycompyle.py", line 68>)
            499 MAKE_FUNCTION            1
            502 STORE_NAME              35 (main)
def main():
	if args is None:
    	args = sys.argv[1:]
	rv = 0
	for filename in args:
	    try:
	        rv = compile(filename)
	    except Exception as err:
	        rv = 1
	        return str(err)

	return hex(rv)

 80         505 LOAD_NAME               36 (__name__)
            508 LOAD_CONST              22 ('__main__')
            511 COMPARE_OP               2 (==)
            514 POP_JUMP_IF_FALSE      536

 81         517 LOAD_NAME                3 (sys)
            520 LOAD_ATTR               37 (exit)
            523 LOAD_NAME               35 (main)
            526 CALL_FUNCTION            0
            529 CALL_FUNCTION            1
            532 POP_TOP             
            533 JUMP_FORWARD             0 (to 536)
        >>  536 LOAD_CONST               2 (None)
            539 RETURN_VALUE        
if __name__=="__main__":
	sys.exit(main())
# FileNames : pycompyle.py
# Python Bytecode : 2.7.18
# Selector <lambda> In Line 18 file pycompyle.pyc
# Timestamp In Code :  (2020-09-05 20:10:01)

# Method Name:       <lambda>
# Filename:          pycompyle.py
# Argument count:    2
# Number of locals:  3
# Stack size:        11
# Flags:             0x00000043 (NOFREE | NEWLOCALS | OPTIMIZED)
# First Line:        18
# Constants:
#    0: None
#    1: ''
#    2: <code object <lambda> at 0xa9f4bf08, file "pycompyle.py", line 18>
# Names:
#    0: join
#    1: range
#    2: len
#    3: chr
#    4: ord
# Varnames:
#	x, y, i
# Positional arguments:
#	x, y
# Local variables:
#    2: i
 18           0 LOAD_CONST               1 ('')
              3 LOAD_ATTR                0 (join)
              6 BUILD_LIST               0
              9 LOAD_GLOBAL              1 (range)
             12 LOAD_GLOBAL              2 (len)
             15 LOAD_FAST                0 (x)
             18 CALL_FUNCTION            1
             21 CALL_FUNCTION            1
             24 GET_ITER            
        >>   25 FOR_ITER                60 (to 88)
             28 STORE_FAST               2 (i)
             31 LOAD_GLOBAL              3 (chr)
             34 LOAD_GLOBAL              4 (ord)
             37 LOAD_FAST                0 (x)
             40 LOAD_FAST                2 (i)
             43 BINARY_SUBSCR       
             44 CALL_FUNCTION            1
             47 LOAD_GLOBAL              4 (ord)
             50 LOAD_FAST                1 (y)
             53 LOAD_CONST               2 (<code object <lambda> at 0xa9f4bf08, file "pycompyle.py", line 18>)
             56 MAKE_FUNCTION            0
             59 LOAD_FAST                2 (i)
             62 LOAD_GLOBAL              2 (len)
             65 LOAD_FAST                1 (y)
             68 CALL_FUNCTION            1
             71 CALL_FUNCTION            2
             74 BINARY_SUBSCR       
             75 CALL_FUNCTION            1
             78 BINARY_XOR          
             79 CALL_FUNCTION            1
             82 LIST_APPEND              2
             85 JUMP_ABSOLUTE           25
        >>   88 CALL_FUNCTION            1
             91 RETURN_VALUE        
# FileNames : pycompyle.py
# Python Bytecode : 2.7.18
# Selector <lambda> In Line 18 file pycompyle.pyc
# Timestamp In Code :  (2020-09-05 20:10:01)

# Method Name:       <lambda>
# Filename:          pycompyle.py
# Argument count:    2
# Number of locals:  2
# Stack size:        2
# Flags:             0x00000053 (NOFREE | NESTED | NEWLOCALS | OPTIMIZED)
# First Line:        18
# Constants:
#    0: None
#    1: 0
# Varnames:
#	x, y
# Positional arguments:
#	x, y
 18           0 LOAD_FAST                0 (x)
              3 LOAD_FAST                1 (y)
              6 BINARY_MODULO       
              7 LOAD_CONST               1 (0)
             10 COMPARE_OP               5 (>=)
             13 POP_JUMP_IF_FALSE       24
             16 LOAD_FAST                0 (x)
             19 LOAD_FAST                1 (y)
             22 BINARY_MODULO       
             23 RETURN_VALUE        
        >>   24 LOAD_FAST                1 (y)
             27 RETURN_VALUE        

return ('').join([ chr(ord(x[i]) ^ ord(y[(lambda x, y: x % y if x % y >= 0 else y)(i, len(y))])) for i in range(len(x)) ])
# FileNames : pycompyle.py
# Python Bytecode : 2.7.18
# Selector __comb_open In Line 22 file pycompyle.pyc
# Timestamp In Code :  (2020-09-05 20:10:01)

# Method Name:       __comb_open
# Filename:          pycompyle.py
# Argument count:    1
# Number of locals:  3
# Stack size:        4
# Flags:             0x0000004f (NOFREE | VARKEYWORDS | VARARGS | NEWLOCALS | OPTIMIZED)
# First Line:        22
# Constants:
#    0: None
# Names:
#    0: __FILES
#    1: StringIO
#    2: __builtin_open
# Varnames:
#	filename, args, kwargs
# Positional arguments:
#	filename
# Local variables:
#    1: args
#    2: kwargs
 23           0 LOAD_FAST                0 (filename)
              3 LOAD_GLOBAL              0 (__FILES)
              6 COMPARE_OP               6 (in)
              9 POP_JUMP_IF_FALSE       29

 24          12 LOAD_GLOBAL              1 (StringIO)
             15 LOAD_ATTR                1 (StringIO)
             18 LOAD_GLOBAL              0 (__FILES)
             21 LOAD_FAST                0 (filename)
             24 BINARY_SUBSCR       
             25 CALL_FUNCTION            1
             28 RETURN_VALUE        

 26     >>   29 LOAD_GLOBAL              2 (__builtin_open)
             32 LOAD_FAST                0 (filename)
             35 LOAD_FAST                1 (args)
             38 LOAD_FAST                2 (kwargs)
             41 CALL_FUNCTION_VAR_KW     1
             44 RETURN_VALUE        
             45 LOAD_CONST               0 (None)
             48 RETURN_VALUE        
if filename in __FILES:
    return StringIO.StringIO(__FILES[filename])
else:
    return __builtin_open(filename, *args, **kwargs)
# FileNames : pycompyle.py
# Python Bytecode : 2.7.18
# Selector __comb_exists In Line 27 file pycompyle.pyc
# Timestamp In Code :  (2020-09-05 20:10:01)

# Method Name:       __comb_exists
# Filename:          pycompyle.py
# Argument count:    1
# Number of locals:  3
# Stack size:        4
# Flags:             0x0000004f (NOFREE | VARKEYWORDS | VARARGS | NEWLOCALS | OPTIMIZED)
# First Line:        27
# Constants:
#    0: None
# Names:
#    0: __FILES
#    1: True
#    2: __os_path_exists
# Varnames:
#	filename, args, kwargs
# Positional arguments:
#	filename
# Local variables:
#    1: args
#    2: kwargs
 28           0 LOAD_FAST                0 (filename)
              3 LOAD_GLOBAL              0 (__FILES)
              6 COMPARE_OP               6 (in)
              9 POP_JUMP_IF_FALSE       16

 29          12 LOAD_GLOBAL              1 (True)
             15 RETURN_VALUE        

 31     >>   16 LOAD_GLOBAL              2 (__os_path_exists)
             19 LOAD_FAST                0 (filename)
             22 LOAD_FAST                1 (args)
             25 LOAD_FAST                2 (kwargs)
             28 CALL_FUNCTION_VAR_KW     1
             31 RETURN_VALUE        
             32 LOAD_CONST               0 (None)
             35 RETURN_VALUE        
if filename in __FILES:
    return True
else:
    return __os_path_exists(filename, *args, **kwargs)
    
# FileNames : pycompyle.py
# Python Bytecode : 2.7.18
# Selector <lambda> In Line 59 file pycompyle.pyc
# Timestamp In Code :  (2020-09-05 20:10:01)

# Method Name:       <lambda>
# Filename:          pycompyle.py
# Argument count:    2
# Number of locals:  2
# Stack size:        3
# Flags:             0x00000043 (NOFREE | NEWLOCALS | OPTIMIZED)
# First Line:        59
# Constants:
#    0: None
# Varnames:
#	x, y
# Positional arguments:
#	x, y
 59           0 LOAD_FAST                0 (x)
              3 LOAD_FAST                0 (x)
              6 LOAD_FAST                1 (y)
              9 CALL_FUNCTION            2
             12 RETURN_VALUE   
return x(x, y)
     
# FileNames : pycompyle.py
# Python Bytecode : 2.7.18
# Selector <lambda> In Line 59 file pycompyle.pyc
# Timestamp In Code :  (2020-09-05 20:10:01)

# Method Name:       <lambda>
# Filename:          pycompyle.py
# Argument count:    2
# Number of locals:  2
# Stack size:        5
# Flags:             0x00000043 (NOFREE | NEWLOCALS | OPTIMIZED)
# First Line:        59
# Constants:
#    0: None
#    1: 256
#    2: ''
# Names:
#    0: chr
# Varnames:
#	x, y
# Positional arguments:
#	x, y
 59           0 LOAD_FAST                1 (y)
              3 POP_JUMP_IF_FALSE       39
              6 LOAD_GLOBAL              0 (chr)
              9 LOAD_FAST                1 (y)
             12 LOAD_CONST               1 (256)
             15 BINARY_MODULO       
             16 CALL_FUNCTION            1
             19 LOAD_FAST                0 (x)
             22 LOAD_FAST                0 (x)
             25 LOAD_FAST                1 (y)
             28 LOAD_CONST               1 (256)
             31 BINARY_FLOOR_DIVIDE 
             32 CALL_FUNCTION            2
             35 BINARY_ADD          
             36 JUMP_IF_TRUE_OR_POP     42
        >>   39 LOAD_CONST               2 ('')
        >>   42 RETURN_VALUE        
return y and chr(y % 256) + x(x, y // 256) or ''

# FileNames : pycompyle.py
# Python Bytecode : 2.7.18
# Selector main In Line 68 file pycompyle.pyc
# Timestamp In Code :  (2020-09-05 20:10:01)

# Method Name:       main
# Filename:          pycompyle.py
# Argument count:    1
# Number of locals:  4
# Stack size:        6
# Flags:             0x00000043 (NOFREE | NEWLOCALS | OPTIMIZED)
# First Line:        68
# Constants:
#    0: None
#    1: 1
#    2: 0
# Names:
#    0: None
#    1: sys
#    2: argv
#    3: compile
#    4: Exception
#    5: str
#    6: hex
# Varnames:
#	args, rv, filename, err
# Positional arguments:
#	args
# Local variables:
#    1: rv
#    2: filename
#    3: err
 69           0 LOAD_FAST                0 (args)
              3 LOAD_CONST               0 (None)
              6 COMPARE_OP               8 (is)
              9 POP_JUMP_IF_FALSE       28

 70          12 LOAD_GLOBAL              1 (sys)
             15 LOAD_ATTR                2 (argv)
             18 LOAD_CONST               1 (1)
             21 SLICE+1             
             22 STORE_FAST               0 (args)
             25 JUMP_FORWARD             0 (to 28)

 71     >>   28 LOAD_CONST               2 (0)
             31 STORE_FAST               1 (rv)

 72          34 SETUP_LOOP              65 (to 102)
             37 LOAD_FAST                0 (args)
             40 GET_ITER            
        >>   41 FOR_ITER                57 (to 101)
             44 STORE_FAST               2 (filename)

 73          47 SETUP_EXCEPT            16 (to 66)

 74          50 LOAD_GLOBAL              3 (compile)
             53 LOAD_FAST                2 (filename)
             56 CALL_FUNCTION            1
             59 STORE_FAST               1 (rv)
             62 POP_BLOCK           
             63 JUMP_ABSOLUTE           41

 75     >>   66 DUP_TOP             
             67 LOAD_GLOBAL              4 (Exception)
             70 COMPARE_OP              10 (exception match)
             73 POP_JUMP_IF_FALSE       97
             76 POP_TOP             
             77 STORE_FAST               3 (err)
             80 POP_TOP             

 76          81 LOAD_CONST               1 (1)
             84 STORE_FAST               1 (rv)

 77          87 LOAD_GLOBAL              5 (str)
             90 LOAD_FAST                3 (err)
             93 CALL_FUNCTION            1
             96 RETURN_VALUE        
        >>   97 END_FINALLY         
             98 JUMP_ABSOLUTE           41
        >>  101 POP_BLOCK           

 78     >>  102 LOAD_GLOBAL              6 (hex)
            105 LOAD_FAST                1 (rv)
            108 CALL_FUNCTION            1
            111 RETURN_VALUE        
if args is None:
    args = sys.argv[1:]
rv = 0
for filename in args:
    try:
        rv = compile(filename)
    except Exception as err:
        rv = 1
        return str(err)

return hex(rv)