# FileNames : <EzzKun>
# Python Bytecode : 3.8.5
# Selector <module> In Line 1 file out.pyc
# Timestamp In Code :  (2020-09-18 18:10:25)

# Method Name:       <module>
# Filename:          <EzzKun>
# Argument count:    0
# Kw-only arguments: 0
# Number of locals:  0
# Stack size:        10
# Flags:             0x00000040 (NOFREE)
# First Line:        1
# Constants:
#    0: 0
#    1: None
#    2: ('datetime',)
#    3: ('*',)
#    4: 'Mozilla/5.0 (Linux; Android 7.0; Redmi Note 4 Build/NRD90M; wv) AppleWebKit/537.36 (KHTML, like Gecko) Version/4.0 Chrome/79.0.3945.93 Mobile Safari/537.36'
#    5: 'application/x-www-form-urlencoded'
#    6: '/'
#    7: 'com.reland.relandicebot'
#    8: 'cross-site'
#    9: 'cors'
#   10: 'gzip, deflate'
#   11: 'id-ID,id;q=0.9,en-US;q=0.8,en;q=0.7'
#   12: 'lang=id'
#   13: ('user-agent', 'content-type', 'accept', 'x-requested-with', 'sec-fetch-site', 'sec-fetch-mode', 'accept-encoding', 'accept-language', 'cookie')
#   14: 'https://www.999doge.com/api/web.aspx'
#   15: '\x1b[0;34m'
#   16: '\x1b[0m'
#   17: '\x1b[1;33m'
#   18: '\x1b[1;32m'
#   19: '\x1b[1;31m'
#   20: '\x1b[0;36m'
#   21: '\x1b[1;35m'
#   22: '\x1b[5;37;42m'
#   23: '\x1b[5;37;41m'
#   24: '{:.8f}'
#   25: '{:0>1.0f}'
#   26: 'Username'
#   27: 'Password'
#   28: 'BaseTrade'
#   29: 'C1'
#   30: 'C2'
#   31: 'TradeCount_1'
#   32: 'TradeCount_2'
#   33: 200
#   34: 'Number Of Trade Out of Limit'
#   35: 'MultiplyOnWin'
#   36: '0'
#   37: 1
#   38: 'MultiplyOnLose'
#   39: 'MaxBaseTrade'
#   40: 'Toogle'
#   41: 'ON'
#   42: 'Max'
#   43: 100000000
#   44: 'ResetOnLoseMaxTrade'
#   45: 'StopOnLoseMaxTrade'
#   46: 'OFF'
#   47: 'ForceTC1AfterLose'
#   48: 'ChangeTCAfterLose'
#   49: 'TargetProfit'
#   50: 'ClientSeed'
#   51: 'RecoveryMultiplier'
#   52: 'RecoveryIncrease'
#   53: 'AddDelayTrade'
#   54: 'AddDelayTradeWin'
#   55: 'AddDelayTradeLose'
#   56: 'StopLoseBalance'
#   57: 'ContinueLastBase'
#   58: 'SmartRecovery'
#   59: -999999999999999999999999999
#   60: -100000000
#   61: 'doge'
#   62: 'Offline'
#   63: <code object withdraw at 0xa8bab020, file "<EzzKun>", line 86>
#   64: 'withdraw'
#   65: <code object harga_license at 0xa8a88f28, file "<EzzKun>", line 107>
#   66: 'harga_license'
#   67: <code object post at 0xa8a03020, file "<EzzKun>", line 121>
#   68: 'post'
#   69: <code object login at 0xa89fff90, file "<EzzKun>", line 125>
#   70: 'login'
#   71: <code object autobet at 0xa89fff28, file "<EzzKun>", line 171>
#   72: 'autobet'
#   73: <code object ainfo at 0xa89ffec0, file "<EzzKun>", line 347>
#   74: 'ainfo'
#   75: <code object verify at 0xa89ffe58, file "<EzzKun>", line 373>
#   76: 'verify'
#   77: <code object register at 0xa89ffc50, file "<EzzKun>", line 382>
#   78: 'register'
#   79: <code object check_license at 0xa89ff9e0, file "<EzzKun>", line 434>
#   80: 'check_license'
#   81: <code object check_license_platinum at 0xa89ff8a8, file "<EzzKun>", line 482>
#   82: 'check_license_platinum'
#   83: <code object gblnc at 0xa89ff840, file "<EzzKun>", line 522>
#   84: 'gblnc'
#   85: 'clear'
#   86: 'https://layscape.xyz/selenia/info.php'
#   87: 'Server Status Code ['
#   88: ']'
#   89: 'Alive'
#   90: 'versi'
#   91: 'Server Down Try Again or Check Latest Version Script'
#   92: 'ERROR CONNECTION TRY AGAIN'
#   93: 'a=GetBalance&s='
#   94: '&Currency=doge'
#   95: 'Balance'
#   96: '\x1b[1;31m====================================================\x1b[0m'
#   97: '\x1b[1;32m[+]\x1b[0m             \x1b[0;36mDO WITH YOUR OWN RISK \x1b[0m           \x1b[1;32m[+]\x1b[0m'
#   98: '\x1b[1;32m[+]\x1b[0m \x1b[1;33mCreator : Layscape\x1b[0m                           \x1b[1;32m[+]\x1b[0m'
#   99: '\x1b[1;32m[+]\x1b[0m \x1b[1;33mVersi Script  V3.0\x1b[0m                           \x1b[1;32m[+]\x1b[0m'
#  100: '\x1b[1;32m[+]\x1b[0m \x1b[1;33mJoin Group Whatsapp For News and Update\x1b[0m      \x1b[1;32m[+]\x1b[0m'
#  101: "Disclaimer : \nScript Not Working Don't Blame Creator :). \nRead/Watch How to Use As Well"
#  102: 'Info :'
#  103: 'notice5'
#  104: 'Information Script :'
#  105: 'Versi :'
#  106: 'Creator :'
#  107: 'created'
#  108: 'Youtube :'
#  109: 'youtube'
#  110: 'Script :'
#  111: 'script'
#  112: '3.0'
#  113: 'New Version'
#  114: 'New Version '
#  115: ' Release'
#  116: 'Please Update'
#  117: 'Type This Command:\n- git stash\n- git pull'
#  118: 'Notice :\n'
#  119: 'notice1'
#  120: 'notice2'
#  121: 'notice3'
#  122: 'notice4'
#  123: '- Attention to Your Connection'
#  124: 'Buy License Here : \nhttps://layscape.xyz/selenia/license'
#  125: ''
#  126: 'Online'
#  127: 'Re-Login for Refresh'
#  128: 'License Out of Date'
#  129: 'Buy New One'
#  130: 'Informasi Status Login :'
#  131: 'Account ID :'
#  132: 'Username :'
#  133: 'Doge Balance :'
#  134: 'Doge Deposit Wallet :'
#  135: 'License Type : '
#  136: 'Free License'
#  137: 'Expired Date : None'
#  138: 'SG Server Status :'
#  139: 'Max Balance : 150 DOGE'
#  140: 'Premium License'
#  141: 'Platinum License'
#  142: 'Date :'
#  143: '%Y-%m-%d'
#  144: 'Expired Date :'
#  145: 'Expired In :'
#  146: 'Days'
#  147: 'Max Balance : Unlimited'
#  148: 'Currency Available : DOGE'
#  149: 'Information Status Login :'
#  150: '\nPilih Menu :'
#  151: '1. Login Premium License'
#  152: '2. Login For Free'
#  153: '3. Login Platinum License'
#  154: '4. Register Account SELENIA'
#  155: '5. Price List License'
#  156: '0. Keluar'
#  157: '6. Start Trade'
#  158: '7. Withdraw'
#  159: '8. Account Information'
#  160: '==>'
#  161: '1'
#  162: '2'
#  163: '3'
#  164: '4'
#  165: '6'
#  166: '5'
#  167: '7'
#  168: '8'
#  169: 'NO MENU SELECTED'
#  170: (0,)
# Names:
#    0: cloudscraper
#    1: sys
#    2: os
#    3: time
#    4: random
#    5: requests
#    6: datetime
#    7: config
#    8: headers
#    9: create_scraper
#   10: scr
#   11: url
#   12: birutua
#   13: putih
#   14: kuning
#   15: hijau
#   16: merah
#   17: biru
#   18: ungu
#   19: bghijau_white
#   20: bgmerah_black
#   21: format
#   22: num_format
#   23: num_PayIn
#   24: account
#   25: Username
#   26: Password
#   27: float
#   28: tradeset
#   29: BaseTrade
#   30: C1
#   31: C2
#   32: int
#   33: TC1
#   34: TC2
#   35: print
#   36: exit
#   37: str
#   38: IncreaseOnWinPercent
#   39: ResetOnWin
#   40: IncreaseOnLosePercent
#   41: ResetOnLose
#   42: MaxBase
#   43: MaxBaseTrade
#   44: ResetOnLoseMaxTrade
#   45: StopOnLoseMaxTrade
#   46: tools
#   47: ForceTC1AfterLose
#   48: ChangeTCAfterLose
#   49: TargetProfit
#   50: ClientSeed
#   51: RecoveryMultiplier
#   52: RecoveryIncrease
#   53: AddDelayTrade
#   54: AddDelayTradeWin
#   55: AddDelayTradeLose
#   56: StopLoseBalance
#   57: ContinueLastBase
#   58: SmartRecovery
#   59: Currency
#   60: statslogin
#   61: limit
#   62: withdraw
#   63: harga_license
#   64: post
#   65: login
#   66: autobet
#   67: ainfo
#   68: verify
#   69: register
#   70: check_license
#   71: check_license_platinum
#   72: gblnc
#   73: system
#   74: get
#   75: srv
#   76: status_code
#   77: status
#   78: json
#   79: info
#   80: version
#   81: Exception
#   82: e
#   83: ses
#   84: getbalance
#   85: req
#   86: dogebalance
#   87: sleep
#   88: Expired
#   89: accid
#   90: dogewallet
#   91: logintype
#   92: statssrv
#   93: now
#   94: mydatetime
#   95: strftime
#   96: userdate
#   97: input
#   98: smenu
  1           0 LOAD_CONST               0 (0)
              2 LOAD_CONST               1 (None)
              4 IMPORT_NAME              0 (cloudscraper)
              6 STORE_NAME               0 (cloudscraper)
              8 LOAD_CONST               0 (0)
             10 LOAD_CONST               1 (None)
             12 IMPORT_NAME              1 (sys)
             14 STORE_NAME               1 (sys)
             16 LOAD_CONST               0 (0)
             18 LOAD_CONST               1 (None)
             20 IMPORT_NAME              2 (os)
             22 STORE_NAME               2 (os)
             24 LOAD_CONST               0 (0)
             26 LOAD_CONST               1 (None)
             28 IMPORT_NAME              3 (time)
             30 STORE_NAME               3 (time)
             32 LOAD_CONST               0 (0)
             34 LOAD_CONST               1 (None)
             36 IMPORT_NAME              4 (random)
             38 STORE_NAME               4 (random)
             40 LOAD_CONST               0 (0)
             42 LOAD_CONST               1 (None)
             44 IMPORT_NAME              5 (requests)
             46 STORE_NAME               5 (requests)

  2          48 LOAD_CONST               0 (0)
             50 LOAD_CONST               2 (('datetime',))
             52 IMPORT_NAME              6 (datetime)
             54 IMPORT_FROM              6 (datetime)
             56 STORE_NAME               6 (datetime)
             58 POP_TOP

  3          60 LOAD_CONST               0 (0)
             62 LOAD_CONST               3 (('*',))
             64 IMPORT_NAME              7 (config)
             66 IMPORT_STAR

  5          68 LOAD_CONST               4 ('Mozilla/5.0 (Linux; Android 7.0; Redmi Note 4 Build/NRD90M; wv) AppleWebKit/537.36 (KHTML, like Gecko) Version/4.0 Chrome/79.0.3945.93 Mobile Safari/537.36')

  6          70 LOAD_CONST               5 ('application/x-www-form-urlencoded')

  7          72 LOAD_CONST               6 ('/')

  8          74 LOAD_CONST               7 ('com.reland.relandicebot')

  9          76 LOAD_CONST               8 ('cross-site')

 10          78 LOAD_CONST               9 ('cors')

 11          80 LOAD_CONST              10 ('gzip, deflate')

 12          82 LOAD_CONST              11 ('id-ID,id;q=0.9,en-US;q=0.8,en;q=0.7')

 13          84 LOAD_CONST              12 ('lang=id')

  4          86 LOAD_CONST              13 (('user-agent', 'content-type', 'accept', 'x-requested-with', 'sec-fetch-site', 'sec-fetch-mode', 'accept-encoding', 'accept-language', 'cookie'))
             88 BUILD_CONST_KEY_MAP      9
             90 STORE_NAME               8 (headers)

 15          92 LOAD_NAME                0 (cloudscraper)
             94 LOAD_METHOD              9 (create_scraper)
             96 CALL_METHOD              0
             98 STORE_NAME              10 (scr)

 16         100 LOAD_CONST              14 ('https://www.999doge.com/api/web.aspx')
            102 STORE_NAME              11 (url)

 17         104 LOAD_CONST              15 ('\x1b[0;34m')
            106 STORE_NAME              12 (birutua)

 18         108 LOAD_CONST              16 ('\x1b[0m')
            110 STORE_NAME              13 (putih)

 19         112 LOAD_CONST              17 ('\x1b[1;33m')
            114 STORE_NAME              14 (kuning)

 20         116 LOAD_CONST              18 ('\x1b[1;32m')
            118 STORE_NAME              15 (hijau)

 21         120 LOAD_CONST              19 ('\x1b[1;31m')
            122 STORE_NAME              16 (merah)

 22         124 LOAD_CONST              20 ('\x1b[0;36m')
            126 STORE_NAME              17 (biru)

 23         128 LOAD_CONST              21 ('\x1b[1;35m')
            130 STORE_NAME              18 (ungu)

 24         132 LOAD_CONST              22 ('\x1b[5;37;42m')
            134 STORE_NAME              19 (bghijau_white)

 25         136 LOAD_CONST              23 ('\x1b[5;37;41m')
            138 STORE_NAME              20 (bgmerah_black)

 26         140 LOAD_CONST              24 ('{:.8f}')
            142 LOAD_ATTR               21 (format)
            144 STORE_NAME              22 (num_format)

 27         146 LOAD_CONST              25 ('{:0>1.0f}')
            148 LOAD_ATTR               21 (format)
            150 STORE_NAME              23 (num_PayIn)

 28         152 LOAD_NAME               24 (account)
            154 LOAD_CONST              26 ('Username')
            156 BINARY_SUBSCR
            158 STORE_NAME              25 (Username)

 29         160 LOAD_NAME               24 (account)
            162 LOAD_CONST              27 ('Password')
            164 BINARY_SUBSCR
            166 STORE_NAME              26 (Password)

 31         168 LOAD_NAME               27 (float)
            170 LOAD_NAME               28 (tradeset)
            172 LOAD_CONST              28 ('BaseTrade')
            174 BINARY_SUBSCR
            176 CALL_FUNCTION            1
            178 STORE_GLOBAL            29 (BaseTrade)

 32         180 LOAD_NAME               27 (float)
            182 LOAD_NAME               28 (tradeset)
            184 LOAD_CONST              29 ('C1')
            186 BINARY_SUBSCR
            188 CALL_FUNCTION            1
            190 STORE_NAME              30 (C1)

 33         192 LOAD_NAME               27 (float)
            194 LOAD_NAME               28 (tradeset)
            196 LOAD_CONST              30 ('C2')
            198 BINARY_SUBSCR
            200 CALL_FUNCTION            1
            202 STORE_NAME              31 (C2)

 34         204 LOAD_NAME               32 (int)
            206 LOAD_NAME               28 (tradeset)
            208 LOAD_CONST              31 ('TradeCount_1')
            210 BINARY_SUBSCR
            212 CALL_FUNCTION            1
            214 STORE_NAME              33 (TC1)

 35         216 LOAD_NAME               32 (int)
            218 LOAD_NAME               28 (tradeset)
            220 LOAD_CONST              32 ('TradeCount_2')
            222 BINARY_SUBSCR
            224 CALL_FUNCTION            1
            226 STORE_NAME              34 (TC2)

 36         228 LOAD_NAME               33 (TC1)
            230 LOAD_CONST              33 (200)
            232 COMPARE_OP               4 (>)
            234 POP_JUMP_IF_TRUE       246
            236 LOAD_NAME               34 (TC2)
            238 LOAD_CONST              33 (200)
            240 COMPARE_OP               4 (>)
            242 EXTENDED_ARG             1
            244 POP_JUMP_IF_FALSE      262

 37     >>  246 LOAD_NAME               35 (print)
            248 LOAD_CONST              34 ('Number Of Trade Out of Limit')
            250 CALL_FUNCTION            1
            252 POP_TOP

 38         254 LOAD_NAME                1 (sys)
            256 LOAD_METHOD             36 (exit)
            258 CALL_METHOD              0
            260 POP_TOP

 39     >>  262 LOAD_NAME               37 (str)
            264 LOAD_NAME               28 (tradeset)
            266 LOAD_CONST              35 ('MultiplyOnWin')
            268 BINARY_SUBSCR
            270 CALL_FUNCTION            1
            272 STORE_NAME              38 (IncreaseOnWinPercent)

 40         274 LOAD_NAME               38 (IncreaseOnWinPercent)
            276 LOAD_CONST              36 ('0')
            278 COMPARE_OP               2 (==)
            280 EXTENDED_ARG             1
            282 POP_JUMP_IF_FALSE      290

 41         284 LOAD_CONST              37 (1)
            286 STORE_NAME              39 (ResetOnWin)
            288 JUMP_FORWARD             4 (to 294)

 43     >>  290 LOAD_CONST               0 (0)
            292 STORE_NAME              39 (ResetOnWin)

 44     >>  294 LOAD_NAME               37 (str)
            296 LOAD_NAME               28 (tradeset)
            298 LOAD_CONST              38 ('MultiplyOnLose')
            300 BINARY_SUBSCR
            302 CALL_FUNCTION            1
            304 STORE_NAME              40 (IncreaseOnLosePercent)

 45         306 LOAD_NAME               40 (IncreaseOnLosePercent)
            308 LOAD_CONST              36 ('0')
            310 COMPARE_OP               2 (==)
            312 EXTENDED_ARG             1
            314 POP_JUMP_IF_FALSE      322

 46         316 LOAD_CONST              37 (1)
            318 STORE_NAME              41 (ResetOnLose)
            320 JUMP_FORWARD             4 (to 326)

 48     >>  322 LOAD_CONST               0 (0)
            324 STORE_NAME              41 (ResetOnLose)

 49     >>  326 LOAD_NAME               28 (tradeset)
            328 LOAD_CONST              39 ('MaxBaseTrade')
            330 BINARY_SUBSCR
            332 LOAD_CONST              40 ('Toogle')
            334 BINARY_SUBSCR
            336 STORE_NAME              42 (MaxBase)

 50         338 LOAD_NAME               42 (MaxBase)
            340 LOAD_CONST              41 ('ON')
            342 COMPARE_OP               2 (==)
            344 EXTENDED_ARG             1
            346 POP_JUMP_IF_FALSE      426

 51         348 LOAD_NAME               27 (float)
            350 LOAD_NAME               28 (tradeset)
            352 LOAD_CONST              39 ('MaxBaseTrade')
            354 BINARY_SUBSCR
            356 LOAD_CONST              42 ('Max')
            358 BINARY_SUBSCR
            360 CALL_FUNCTION            1
            362 LOAD_CONST              43 (100000000)
            364 BINARY_MULTIPLY
            366 STORE_GLOBAL            43 (MaxBaseTrade)

 52         368 LOAD_NAME               28 (tradeset)
            370 LOAD_CONST              39 ('MaxBaseTrade')
            372 BINARY_SUBSCR
            374 LOAD_CONST              44 ('ResetOnLoseMaxTrade')
            376 BINARY_SUBSCR
            378 LOAD_CONST              41 ('ON')
            380 COMPARE_OP               2 (==)
            382 EXTENDED_ARG             1
            384 POP_JUMP_IF_FALSE      392

 53         386 LOAD_CONST              37 (1)
            388 STORE_NAME              44 (ResetOnLoseMaxTrade)
            390 JUMP_FORWARD             4 (to 396)

 55     >>  392 LOAD_CONST               0 (0)
            394 STORE_NAME              44 (ResetOnLoseMaxTrade)

 56     >>  396 LOAD_NAME               28 (tradeset)
            398 LOAD_CONST              39 ('MaxBaseTrade')
            400 BINARY_SUBSCR
            402 LOAD_CONST              45 ('StopOnLoseMaxTrade')
            404 BINARY_SUBSCR
            406 LOAD_CONST              41 ('ON')
            408 COMPARE_OP               2 (==)
            410 EXTENDED_ARG             1
            412 POP_JUMP_IF_FALSE      420

 57         414 LOAD_CONST              37 (1)
            416 STORE_NAME              45 (StopOnLoseMaxTrade)
            418 JUMP_FORWARD             4 (to 424)

 59     >>  420 LOAD_CONST               0 (0)
            422 STORE_NAME              45 (StopOnLoseMaxTrade)
        >>  424 JUMP_FORWARD            22 (to 448)

 60     >>  426 LOAD_NAME               42 (MaxBase)
            428 LOAD_CONST              46 ('OFF')
            430 COMPARE_OP               2 (==)
            432 EXTENDED_ARG             1
            434 POP_JUMP_IF_FALSE      448

 61         436 LOAD_CONST               0 (0)
            438 STORE_GLOBAL            43 (MaxBaseTrade)

 62         440 LOAD_CONST               0 (0)
            442 STORE_NAME              44 (ResetOnLoseMaxTrade)

 63         444 LOAD_CONST               0 (0)
            446 STORE_NAME              45 (StopOnLoseMaxTrade)

 66     >>  448 LOAD_NAME               46 (tools)
            450 LOAD_CONST              47 ('ForceTC1AfterLose')
            452 BINARY_SUBSCR
            454 STORE_NAME              47 (ForceTC1AfterLose)

 67         456 LOAD_NAME               46 (tools)
            458 LOAD_CONST              48 ('ChangeTCAfterLose')
            460 BINARY_SUBSCR
            462 LOAD_CONST              40 ('Toogle')
            464 BINARY_SUBSCR
            466 STORE_NAME              48 (ChangeTCAfterLose)

 68         468 LOAD_NAME               27 (float)
            470 LOAD_NAME               46 (tools)
            472 LOAD_CONST              49 ('TargetProfit')
            474 BINARY_SUBSCR
            476 CALL_FUNCTION            1
            478 STORE_NAME              49 (TargetProfit)

 69         480 LOAD_NAME               32 (int)
            482 LOAD_NAME               28 (tradeset)
            484 LOAD_CONST              50 ('ClientSeed')
            486 BINARY_SUBSCR
            488 CALL_FUNCTION            1
            490 STORE_NAME              50 (ClientSeed)

 70         492 LOAD_NAME               27 (float)
            494 LOAD_NAME               46 (tools)
            496 LOAD_CONST              51 ('RecoveryMultiplier')
            498 BINARY_SUBSCR
            500 CALL_FUNCTION            1
            502 STORE_NAME              51 (RecoveryMultiplier)

 71         504 LOAD_NAME               27 (float)
            506 LOAD_NAME               46 (tools)
            508 LOAD_CONST              52 ('RecoveryIncrease')
            510 BINARY_SUBSCR
            512 CALL_FUNCTION            1
            514 STORE_NAME              52 (RecoveryIncrease)

 72         516 LOAD_NAME               27 (float)
            518 LOAD_NAME               46 (tools)
            520 LOAD_CONST              53 ('AddDelayTrade')
            522 BINARY_SUBSCR
            524 CALL_FUNCTION            1
            526 STORE_NAME              53 (AddDelayTrade)

 73         528 LOAD_NAME               27 (float)
            530 LOAD_NAME               46 (tools)
            532 LOAD_CONST              54 ('AddDelayTradeWin')
            534 BINARY_SUBSCR
            536 CALL_FUNCTION            1
            538 STORE_NAME              54 (AddDelayTradeWin)

 74         540 LOAD_NAME               27 (float)
            542 LOAD_NAME               46 (tools)
            544 LOAD_CONST              55 ('AddDelayTradeLose')
            546 BINARY_SUBSCR
            548 CALL_FUNCTION            1
            550 STORE_NAME              55 (AddDelayTradeLose)

 75         552 LOAD_NAME               27 (float)
            554 LOAD_NAME               46 (tools)
            556 LOAD_CONST              56 ('StopLoseBalance')
            558 BINARY_SUBSCR
            560 CALL_FUNCTION            1
            562 STORE_NAME              56 (StopLoseBalance)

 76         564 LOAD_NAME               46 (tools)
            566 LOAD_CONST              57 ('ContinueLastBase')
            568 BINARY_SUBSCR
            570 STORE_GLOBAL            57 (ContinueLastBase)

 77         572 LOAD_NAME               46 (tools)
            574 LOAD_CONST              58 ('SmartRecovery')
            576 BINARY_SUBSCR
            578 STORE_NAME              58 (SmartRecovery)

import cloudscraper, sys, os, time, random, requests
from datetime import datetime
from config import *
headers = {'user-agent':'Mozilla/5.0 (Linux; Android 7.0; Redmi Note 4 Build/NRD90M; wv) AppleWebKit/537.36 (KHTML, like Gecko) Version/4.0 Chrome/79.0.3945.93 Mobile Safari/537.36', 
 'content-type':'application/x-www-form-urlencoded', 
 'accept':'/', 
 'x-requested-with':'com.reland.relandicebot', 
 'sec-fetch-site':'cross-site', 
 'sec-fetch-mode':'cors', 
 'accept-encoding':'gzip, deflate', 
 'accept-language':'id-ID,id;q=0.9,en-US;q=0.8,en;q=0.7', 
 'cookie':'lang=id'}
scr = cloudscraper.create_scraper()
url = 'https://www.999doge.com/api/web.aspx'
birutua = '\x1b[0;34m'
putih = '\x1b[0m'
kuning = '\x1b[1;33m'
hijau = '\x1b[1;32m'
merah = '\x1b[1;31m'
biru = '\x1b[0;36m'
ungu = '\x1b[1;35m'
bghijau_white = '\x1b[5;37;42m'
bgmerah_black = '\x1b[5;37;41m'
num_format = '{:.8f}'.format
num_PayIn = '{:0>1.0f}'.format
Username = account['Username']
Password = account['Password']
BaseTrade = float(tradeset['BaseTrade'])
C1 = float(tradeset['C1'])
C2 = float(tradeset['C2'])
TC1 = int(tradeset['TradeCount_1'])
TC2 = int(tradeset['TradeCount_2'])
if TC1 > 200 or (TC2 > 200):
    print('Number Of Trade Out of Limit')
    sys.exit()
IncreaseOnWinPercent = str(tradeset['MultiplyOnWin'])
if IncreaseOnWinPercent == '0':
    ResetOnWin = 1
else:
    ResetOnWin = 0
IncreaseOnLosePercent = str(tradeset['MultiplyOnLose'])
if IncreaseOnLosePercent == '0':
    ResetOnLose = 1
else:
    ResetOnLose = 0
MaxBase = tradeset['MaxBaseTrade']['Toogle']
if MaxBase == 'ON':
    MaxBaseTrade = float(tradeset['MaxBaseTrade']['Max']) * 100000000
    if tradeset['MaxBaseTrade']['ResetOnLoseMaxTrade'] == 'ON':
        ResetOnLoseMaxTrade = 1
    else:
        ResetOnLoseMaxTrade = 0
    if tradeset['MaxBaseTrade']['StopOnLoseMaxTrade'] == 'ON':
        StopOnLoseMaxTrade = 1
    else:
        StopOnLoseMaxTrade = 0
elif MaxBase == 'OFF':
    MaxBaseTrade = 0
    ResetOnLoseMaxTrade = 0
    StopOnLoseMaxTrade = 0
ForceTC1AfterLose = tools['ForceTC1AfterLose']
ChangeTCAfterLose = tools['ChangeTCAfterLose']['Toogle']
TargetProfit = float(tools['TargetProfit'])
ClientSeed = int(tradeset['ClientSeed'])
RecoveryMultiplier = float(tools['RecoveryMultiplier'])
RecoveryIncrease = float(tools['RecoveryIncrease'])
AddDelayTrade = float(tools['AddDelayTrade'])
AddDelayTradeWin = float(tools['AddDelayTradeWin'])
AddDelayTradeLose = float(tools['AddDelayTradeLose'])
StopLoseBalance = float(tools['StopLoseBalance'])
ContinueLastBase = tools['ContinueLastBase']
SmartRecovery = tools['SmartRecovery']

 78         580 LOAD_NAME               56 (StopLoseBalance)
            582 LOAD_CONST              36 ('0')
            584 COMPARE_OP               2 (==)
            586 EXTENDED_ARG             2
            588 POP_JUMP_IF_TRUE       600
            590 LOAD_NAME               56 (StopLoseBalance)
            592 LOAD_CONST               0 (0)
            594 COMPARE_OP               2 (==)
            596 EXTENDED_ARG             2
            598 POP_JUMP_IF_FALSE      606

 79     >>  600 LOAD_CONST              59 (-999999999999999999999999999)
            602 STORE_NAME              56 (StopLoseBalance)
            604 JUMP_FORWARD            28 (to 634)

 80     >>  606 LOAD_NAME               56 (StopLoseBalance)
            608 LOAD_CONST              36 ('0')
            610 COMPARE_OP               3 (!=)
            612 EXTENDED_ARG             2
            614 POP_JUMP_IF_TRUE       626
            616 LOAD_NAME               56 (StopLoseBalance)
            618 LOAD_CONST               0 (0)
            620 COMPARE_OP               3 (!=)
            622 EXTENDED_ARG             2
            624 POP_JUMP_IF_FALSE      634

 81     >>  626 LOAD_NAME               56 (StopLoseBalance)
            628 LOAD_CONST              60 (-100000000)
            630 BINARY_MULTIPLY
            632 STORE_NAME              56 (StopLoseBalance)

 82     >>  634 LOAD_CONST              61 ('doge')
            636 STORE_NAME              59 (Currency)

 84         638 LOAD_CONST              62 ('Offline')
            640 STORE_GLOBAL            60 (statslogin)

 85         642 LOAD_CONST               0 (0)
            644 STORE_NAME              61 (limit)
# --- skip function ---
 86         646 LOAD_CONST              63 (<code object withdraw at 0xa8bab020, file "<EzzKun>", line 86>)
            648 LOAD_CONST              64 ('withdraw')
            650 MAKE_FUNCTION            0
            652 STORE_NAME              62 (withdraw)

107         654 LOAD_CONST              65 (<code object harga_license at 0xa8a88f28, file "<EzzKun>", line 107>)
            656 LOAD_CONST              66 ('harga_license')
            658 MAKE_FUNCTION            0
            660 STORE_NAME              63 (harga_license)

121         662 LOAD_CONST              67 (<code object post at 0xa8a03020, file "<EzzKun>", line 121>)
            664 LOAD_CONST              68 ('post')
            666 MAKE_FUNCTION            0
            668 STORE_NAME              64 (post)

125         670 LOAD_CONST              69 (<code object login at 0xa89fff90, file "<EzzKun>", line 125>)
            672 LOAD_CONST              70 ('login')
            674 MAKE_FUNCTION            0
            676 STORE_NAME              65 (login)

171         678 LOAD_CONST             170 ((0,))
            680 LOAD_CONST              71 (<code object autobet at 0xa89fff28, file "<EzzKun>", line 171>)
            682 LOAD_CONST              72 ('autobet')
            684 MAKE_FUNCTION            1 (defaults)
            686 STORE_NAME              66 (autobet)

347         688 LOAD_CONST              73 (<code object ainfo at 0xa89ffec0, file "<EzzKun>", line 347>)
            690 LOAD_CONST              74 ('ainfo')
            692 MAKE_FUNCTION            0
            694 STORE_NAME              67 (ainfo)

373         696 LOAD_CONST              75 (<code object verify at 0xa89ffe58, file "<EzzKun>", line 373>)
            698 LOAD_CONST              76 ('verify')
            700 MAKE_FUNCTION            0
            702 STORE_NAME              68 (verify)

382         704 LOAD_CONST              77 (<code object register at 0xa89ffc50, file "<EzzKun>", line 382>)
            706 LOAD_CONST              78 ('register')
            708 MAKE_FUNCTION            0
            710 STORE_NAME              69 (register)

434         712 LOAD_CONST              79 (<code object check_license at 0xa89ff9e0, file "<EzzKun>", line 434>)
            714 LOAD_CONST              80 ('check_license')
            716 MAKE_FUNCTION            0
            718 STORE_NAME              70 (check_license)

482         720 LOAD_CONST              81 (<code object check_license_platinum at 0xa89ff8a8, file "<EzzKun>", line 482>)
            722 LOAD_CONST              82 ('check_license_platinum')
            724 MAKE_FUNCTION            0
            726 STORE_NAME              71 (check_license_platinum)

522         728 LOAD_CONST              83 (<code object gblnc at 0xa89ff840, file "<EzzKun>", line 522>)
            730 LOAD_CONST              84 ('gblnc')
            732 MAKE_FUNCTION            0
            734 STORE_NAME              72 (gblnc)
# --- all function i'am saved to file in dir ``object``

529         736 SETUP_FINALLY           86 (to 824)

530         738 LOAD_NAME                2 (os)
            740 LOAD_METHOD             73 (system)
            742 LOAD_CONST              85 ('clear')
            744 CALL_METHOD              1
            746 POP_TOP

531         748 LOAD_NAME               10 (scr)
            750 LOAD_METHOD             74 (get)
            752 LOAD_CONST              86 ('https://layscape.xyz/selenia/info.php')
            754 CALL_METHOD              1
            756 STORE_NAME              75 (srv)

532         758 LOAD_NAME               75 (srv)
            760 LOAD_ATTR               76 (status_code)
            762 STORE_NAME              77 (status)

533         764 LOAD_NAME               35 (print)
            766 LOAD_CONST              87 ('Server Status Code [')
            768 LOAD_NAME               77 (status)
            770 LOAD_CONST              88 (']')
            772 CALL_FUNCTION            3
            774 POP_TOP

534         776 LOAD_NAME               77 (status)
            778 LOAD_CONST              33 (200)
            780 COMPARE_OP               2 (==)
            782 EXTENDED_ARG             3
            784 POP_JUMP_IF_FALSE      820

535         786 LOAD_NAME               35 (print)
            788 LOAD_NAME               15 (hijau)
            790 LOAD_CONST              89 ('Alive')
            792 BINARY_ADD
            794 LOAD_NAME               13 (putih)
            796 BINARY_ADD
            798 CALL_FUNCTION            1
            800 POP_TOP

536         802 LOAD_NAME               75 (srv)
            804 LOAD_METHOD             78 (json)
            806 CALL_METHOD              0
            808 STORE_NAME              79 (info)

537         810 LOAD_NAME               79 (info)
            812 LOAD_CONST              90 ('versi')
            814 BINARY_SUBSCR
            816 STORE_NAME              80 (version)
            818 JUMP_FORWARD             0 (to 820)

539     >>  820 POP_BLOCK
            822 JUMP_FORWARD            86 (to 910)

540     >>  824 DUP_TOP
            826 LOAD_NAME               81 (Exception)
            828 COMPARE_OP              10 (exception match)
            830 EXTENDED_ARG             3
            832 POP_JUMP_IF_FALSE      908
            834 POP_TOP
            836 STORE_NAME              82 (e)
            838 POP_TOP
            840 SETUP_FINALLY           54 (to 896)

541         842 LOAD_NAME               35 (print)
            844 LOAD_NAME               16 (merah)
            846 LOAD_CONST              91 ('Server Down Try Again or Check Latest Version Script')
            848 BINARY_ADD
            850 LOAD_NAME               13 (putih)
            852 BINARY_ADD
            854 CALL_FUNCTION            1
            856 POP_TOP

542         858 LOAD_NAME               35 (print)
            860 LOAD_CONST              87 ('Server Status Code [')
            862 LOAD_NAME               77 (status)
            864 LOAD_CONST              88 (']')
            866 CALL_FUNCTION            3
            868 POP_TOP

543         870 LOAD_NAME               35 (print)
            872 LOAD_NAME               16 (merah)
            874 LOAD_CONST              92 ('ERROR CONNECTION TRY AGAIN')
            876 LOAD_NAME               13 (putih)
            878 BINARY_ADD
            880 CALL_FUNCTION            2
            882 POP_TOP

544         884 LOAD_NAME                1 (sys)
            886 LOAD_METHOD             36 (exit)
            888 CALL_METHOD              0
            890 POP_TOP
            892 POP_BLOCK
            894 BEGIN_FINALLY
        >>  896 LOAD_CONST               1 (None)
            898 STORE_NAME              82 (e)
            900 DELETE_NAME             82 (e)
            902 END_FINALLY
            904 POP_EXCEPT
            906 JUMP_FORWARD             2 (to 910)
        >>  908 END_FINALLY
if StopLoseBalance == '0' or StopLoseBalance == 0:
    StopLoseBalance = -999999999999999999999999999
else:
    if StopLoseBalance != '0' or (StopLoseBalance != 0):
        StopLoseBalance = StopLoseBalance * -100000000
Currency = 'doge'
statslogin = 'Offline'
limit = 0
try:
    os.system('clear')
    srv = scr.get('https://layscape.xyz/selenia/info.php')
    status = srv.status_code
    print('Server Status Code [', status, ']')
    if status == 200:
        print(hijau + 'Alive' + putih)
        info = srv.json()
        version = info['versi']
    else:
        pass
except Exception as e:
    try:
        print(merah + 'Server Down Try Again or Check Latest Version Script' + putih)
        print('Server Status Code [', status, ']')
        print(merah, 'ERROR CONNECTION TRY AGAIN' + putih)
        sys.exit()
    finally:
        e = None
        del e

545     >>  910 LOAD_NAME               77 (status)
            912 LOAD_CONST              33 (200)
            914 COMPARE_OP               2 (==)
            916 EXTENDED_ARG             8
            918 POP_JUMP_IF_FALSE     2064

546         920 SETUP_FINALLY           36 (to 958)

547         922 LOAD_CONST              93 ('a=GetBalance&s=')
            924 LOAD_GLOBAL             83 (ses)
            926 BINARY_ADD
            928 LOAD_CONST              94 ('&Currency=doge')
            930 BINARY_ADD
            932 STORE_NAME              84 (getbalance)

548         934 LOAD_NAME               64 (post)
            936 LOAD_NAME               84 (getbalance)
            938 CALL_FUNCTION            1
            940 POP_TOP

549         942 LOAD_GLOBAL             85 (req)
            944 LOAD_CONST              95 ('Balance')
            946 BINARY_SUBSCR
            948 LOAD_CONST              43 (100000000)
            950 BINARY_TRUE_DIVIDE
            952 STORE_GLOBAL            86 (dogebalance)
            954 POP_BLOCK
            956 JUMP_FORWARD            12 (to 970)

550     >>  958 POP_TOP
            960 POP_TOP
            962 POP_TOP

551         964 POP_EXCEPT
            966 JUMP_FORWARD             2 (to 970)
            968 END_FINALLY

552     >>  970 LOAD_NAME                3 (time)
            972 LOAD_METHOD             87 (sleep)
            974 LOAD_CONST              37 (1)
            976 CALL_METHOD              1
            978 POP_TOP

553         980 LOAD_NAME                2 (os)
            982 LOAD_METHOD             73 (system)
            984 LOAD_CONST              85 ('clear')
            986 CALL_METHOD              1
            988 POP_TOP

554         990 LOAD_NAME               35 (print)
            992 LOAD_CONST              96 ('\x1b[1;31m====================================================\x1b[0m')
            994 CALL_FUNCTION            1
            996 POP_TOP

555         998 LOAD_NAME               35 (print)
           1000 LOAD_CONST              97 ('\x1b[1;32m[+]\x1b[0m             \x1b[0;36mDO WITH YOUR OWN RISK \x1b[0m           \x1b[1;32m[+]\x1b[0m')
           1002 CALL_FUNCTION            1
           1004 POP_TOP

556        1006 LOAD_NAME               35 (print)
           1008 LOAD_CONST              98 ('\x1b[1;32m[+]\x1b[0m \x1b[1;33mCreator : Layscape\x1b[0m                           \x1b[1;32m[+]\x1b[0m')
           1010 CALL_FUNCTION            1
           1012 POP_TOP

557        1014 LOAD_NAME               35 (print)
           1016 LOAD_CONST              99 ('\x1b[1;32m[+]\x1b[0m \x1b[1;33mVersi Script  V3.0\x1b[0m                           \x1b[1;32m[+]\x1b[0m')
           1018 CALL_FUNCTION            1
           1020 POP_TOP

558        1022 LOAD_NAME               35 (print)
           1024 LOAD_CONST             100 ('\x1b[1;32m[+]\x1b[0m \x1b[1;33mJoin Group Whatsapp For News and Update\x1b[0m      \x1b[1;32m[+]\x1b[0m')
           1026 CALL_FUNCTION            1
           1028 POP_TOP

559        1030 LOAD_NAME               35 (print)
           1032 LOAD_CONST              96 ('\x1b[1;31m====================================================\x1b[0m')
           1034 CALL_FUNCTION            1
           1036 POP_TOP

560        1038 LOAD_NAME               35 (print)
           1040 LOAD_CONST             101 ("Disclaimer : \nScript Not Working Don't Blame Creator :). \nRead/Watch How to Use As Well")
           1042 CALL_FUNCTION            1
           1044 POP_TOP

561        1046 LOAD_NAME               35 (print)
           1048 LOAD_CONST              96 ('\x1b[1;31m====================================================\x1b[0m')
           1050 CALL_FUNCTION            1
           1052 POP_TOP

562        1054 LOAD_NAME               35 (print)
           1056 LOAD_NAME               14 (kuning)
           1058 LOAD_CONST             102 ('Info :')
           1060 BINARY_ADD
           1062 LOAD_NAME               79 (info)
           1064 LOAD_CONST             103 ('notice5')
           1066 BINARY_SUBSCR
           1068 BINARY_ADD
           1070 LOAD_NAME               13 (putih)
           1072 BINARY_ADD
           1074 CALL_FUNCTION            1
           1076 POP_TOP

563        1078 LOAD_NAME               35 (print)
           1080 LOAD_CONST              96 ('\x1b[1;31m====================================================\x1b[0m')
           1082 CALL_FUNCTION            1
           1084 POP_TOP

564        1086 LOAD_NAME               35 (print)
           1088 LOAD_NAME               15 (hijau)
           1090 LOAD_CONST             104 ('Information Script :')
           1092 BINARY_ADD
           1094 CALL_FUNCTION            1
           1096 POP_TOP

565        1098 LOAD_NAME               35 (print)
           1100 LOAD_CONST             105 ('Versi :')
           1102 LOAD_NAME               79 (info)
           1104 LOAD_CONST              90 ('versi')
           1106 BINARY_SUBSCR
           1108 CALL_FUNCTION            2
           1110 POP_TOP

566        1112 LOAD_NAME               35 (print)
           1114 LOAD_CONST             106 ('Creator :')
           1116 LOAD_NAME               79 (info)
           1118 LOAD_CONST             107 ('created')
           1120 BINARY_SUBSCR
           1122 CALL_FUNCTION            2
           1124 POP_TOP

567        1126 LOAD_NAME               35 (print)
           1128 LOAD_CONST             108 ('Youtube :')
           1130 LOAD_NAME               79 (info)
           1132 LOAD_CONST             109 ('youtube')
           1134 BINARY_SUBSCR
           1136 CALL_FUNCTION            2
           1138 POP_TOP

568        1140 LOAD_NAME               35 (print)
           1142 LOAD_CONST             110 ('Script :')
           1144 LOAD_NAME               79 (info)
           1146 LOAD_CONST             111 ('script')
           1148 BINARY_SUBSCR
           1150 LOAD_NAME               13 (putih)
           1152 BINARY_ADD
           1154 CALL_FUNCTION            2
           1156 POP_TOP

569        1158 LOAD_CONST             112 ('3.0')
           1160 LOAD_NAME               80 (version)
           1162 COMPARE_OP               2 (==)
           1164 EXTENDED_ARG             4
           1166 POP_JUMP_IF_FALSE     1186 # this is if

570        1168 LOAD_NAME               35 (print)
           1170 LOAD_NAME               15 (hijau)
           1172 LOAD_CONST             113 ('New Version')
           1174 BINARY_ADD
           1176 LOAD_NAME               13 (putih)
           1178 BINARY_ADD
           1180 CALL_FUNCTION            1
           1182 POP_TOP
           1184 JUMP_FORWARD            74 (to 1260)

571     >> 1186 LOAD_NAME               80 (version)
           1188 LOAD_CONST             112 ('3.0')
           1190 COMPARE_OP               4 (>)
           1192 EXTENDED_ARG             4
           1194 POP_JUMP_IF_FALSE     1260 # this is elif

572        1196 LOAD_NAME               35 (print)
           1198 LOAD_NAME               16 (merah)
           1200 LOAD_CONST             114 ('New Version ')
           1202 BINARY_ADD
           1204 LOAD_NAME               80 (version)
           1206 BINARY_ADD
           1208 LOAD_CONST             115 (' Release')
           1210 BINARY_ADD
           1212 LOAD_NAME               13 (putih)
           1214 BINARY_ADD
           1216 CALL_FUNCTION            1
           1218 POP_TOP

573        1220 LOAD_NAME               35 (print)
           1222 LOAD_NAME               16 (merah)
           1224 LOAD_CONST             116 ('Please Update')
           1226 BINARY_ADD
           1228 LOAD_NAME               13 (putih)
           1230 BINARY_ADD
           1232 CALL_FUNCTION            1
           1234 POP_TOP

574        1236 LOAD_NAME               35 (print)
           1238 LOAD_NAME               15 (hijau)
           1240 LOAD_CONST             117 ('Type This Command:\n- git stash\n- git pull')
           1242 BINARY_ADD
           1244 LOAD_NAME               13 (putih)
           1246 BINARY_ADD
           1248 CALL_FUNCTION            1
           1250 POP_TOP

575        1252 LOAD_NAME                1 (sys)
           1254 LOAD_METHOD             36 (exit)
           1256 CALL_METHOD              0
           1258 POP_TOP

576     >> 1260 LOAD_NAME               35 (print)
           1262 LOAD_NAME               14 (kuning)
           1264 LOAD_CONST             118 ('Notice :\n')
           1266 BINARY_ADD
           1268 LOAD_NAME               79 (info)
           1270 LOAD_CONST             119 ('notice1')
           1272 BINARY_SUBSCR
           1274 BINARY_ADD
           1276 CALL_FUNCTION            1
           1278 POP_TOP

577        1280 LOAD_NAME               35 (print)
           1282 LOAD_NAME               79 (info)
           1284 LOAD_CONST             120 ('notice2')
           1286 BINARY_SUBSCR
           1288 CALL_FUNCTION            1
           1290 POP_TOP

578        1292 LOAD_NAME               35 (print)
           1294 LOAD_NAME               79 (info)
           1296 LOAD_CONST             121 ('notice3')
           1298 BINARY_SUBSCR
           1300 CALL_FUNCTION            1
           1302 POP_TOP

579        1304 LOAD_NAME               35 (print)
           1306 LOAD_NAME               79 (info)
           1308 LOAD_CONST             122 ('notice4')
           1310 BINARY_SUBSCR
           1312 CALL_FUNCTION            1
           1314 POP_TOP

580        1316 LOAD_NAME               35 (print)
           1318 LOAD_CONST             123 ('- Attention to Your Connection')
           1320 LOAD_NAME               13 (putih)
           1322 BINARY_ADD
           1324 CALL_FUNCTION            1
           1326 POP_TOP

581        1328 LOAD_NAME               35 (print)
           1330 LOAD_CONST             124 ('Buy License Here : \nhttps://layscape.xyz/selenia/license')
           1332 CALL_FUNCTION            1
           1334 POP_TOP

582        1336 LOAD_NAME               35 (print)
           1338 LOAD_CONST             125 ('')
           1340 CALL_FUNCTION            1
           1342 POP_TOP

583        1344 LOAD_GLOBAL             60 (statslogin)
           1346 LOAD_CONST             126 ('Online')
           1348 COMPARE_OP               2 (==)
           1350 EXTENDED_ARG             6
           1352 POP_JUMP_IF_FALSE     1666

584        1354 LOAD_NAME               35 (print)
           1356 LOAD_NAME               15 (hijau)
           1358 LOAD_CONST             127 ('Re-Login for Refresh')
           1360 BINARY_ADD
           1362 LOAD_NAME               13 (putih)
           1364 CALL_FUNCTION            2
           1366 POP_TOP
if status == 200:
    try:
        getbalance = 'a=GetBalance&s=' + ses + '&Currency=doge'
        post(getbalance)
        dogebalance = req['Balance'] / 100000000
    except:
        pass
    else:
        time.sleep(1)
        os.system('clear')
        print('\x1b[1;31m====================================================\x1b[0m')
        print('\x1b[1;32m[+]\x1b[0m             \x1b[0;36mDO WITH YOUR OWN RISK \x1b[0m           \x1b[1;32m[+]\x1b[0m')
        print('\x1b[1;32m[+]\x1b[0m \x1b[1;33mCreator : Layscape\x1b[0m                           \x1b[1;32m[+]\x1b[0m')
        print('\x1b[1;32m[+]\x1b[0m \x1b[1;33mVersi Script  V3.0\x1b[0m                           \x1b[1;32m[+]\x1b[0m')
        print('\x1b[1;32m[+]\x1b[0m \x1b[1;33mJoin Group Whatsapp For News and Update\x1b[0m      \x1b[1;32m[+]\x1b[0m')
        print('\x1b[1;31m====================================================\x1b[0m')
        print("Disclaimer : \nScript Not Working Don't Blame Creator :). \nRead/Watch How to Use As Well")
        print('\x1b[1;31m====================================================\x1b[0m')
        print(kuning + 'Info :' + info['notice5'] + putih)
        print('\x1b[1;31m====================================================\x1b[0m')
        print(hijau + 'Information Script :')
        print('Versi :', info['versi'])
        print('Creator :', info['created'])
        print('Youtube :', info['youtube'])
        print('Script :', info['script'] + putih)
        if '3.0' == version:
            print(hijau + 'New Version' + putih)
        elif  version > '3.0': # -> float required not str
            print(merah + 'New Version ' + version + ' Release' + putih)
            print(merah + 'Please Update' + putih)
            print(hijau + 'Type This Command:\n- git stash\n- git pull' + putih)
            sys.exit()
            print(kuning + 'Notice :\n' + info['notice1'])
            print(info['notice2'])
            print(info['notice3'])
            print(info['notice4'])
            print('- Attention to Your Connection' + putih)
            print('Buy License Here : \nhttps://layscape.xyz/selenia/license')
            print('')
            if statslogin == 'Online':
                print(hijau + 'Re-Login for Refresh', putih)
else:
    pass
585        1368 SETUP_FINALLY           56 (to 1426)

586        1370 LOAD_GLOBAL             88 (Expired)
           1372 LOAD_CONST               0 (0)
           1374 COMPARE_OP               1 (<=)
           1376 EXTENDED_ARG             5
           1378 POP_JUMP_IF_FALSE     1422

587        1380 LOAD_NAME               35 (print)
           1382 LOAD_NAME               16 (merah)
           1384 LOAD_CONST             128 ('License Out of Date')
           1386 BINARY_ADD
           1388 LOAD_NAME               13 (putih)
           1390 BINARY_ADD
           1392 CALL_FUNCTION            1
           1394 POP_TOP

588        1396 LOAD_NAME               35 (print)
           1398 LOAD_NAME               14 (kuning)
           1400 LOAD_CONST             129 ('Buy New One')
           1402 BINARY_ADD
           1404 LOAD_NAME               13 (putih)
           1406 BINARY_ADD
           1408 CALL_FUNCTION            1
           1410 POP_TOP

589        1412 LOAD_NAME                1 (sys)
           1414 LOAD_METHOD             36 (exit)
           1416 CALL_METHOD              0
           1418 POP_TOP
           1420 JUMP_FORWARD             0 (to 1422)

591     >> 1422 POP_BLOCK
           1424 JUMP_FORWARD            12 (to 1438)

592     >> 1426 POP_TOP
           1428 POP_TOP
           1430 POP_TOP

593        1432 POP_EXCEPT
           1434 JUMP_FORWARD             2 (to 1438)
           1436 END_FINALLY

594     >> 1438 LOAD_NAME               35 (print)
           1440 LOAD_CONST             130 ('Informasi Status Login :')
           1442 LOAD_NAME               15 (hijau)
           1444 LOAD_GLOBAL             60 (statslogin)
           1446 BINARY_ADD
           1448 LOAD_NAME               13 (putih)
           1450 BINARY_ADD
           1452 CALL_FUNCTION            2
           1454 POP_TOP

595        1456 LOAD_NAME               35 (print)
           1458 LOAD_CONST             131 ('Account ID :')
           1460 LOAD_GLOBAL             89 (accid)
           1462 CALL_FUNCTION            2
           1464 POP_TOP

596        1466 LOAD_NAME               35 (print)
           1468 LOAD_CONST             132 ('Username :')
           1470 LOAD_NAME               25 (Username)
           1472 CALL_FUNCTION            2
           1474 POP_TOP

597        1476 LOAD_NAME               35 (print)
           1478 LOAD_CONST             133 ('Doge Balance :')
           1480 LOAD_NAME               22 (num_format)
           1482 LOAD_GLOBAL             86 (dogebalance)
           1484 CALL_FUNCTION            1
           1486 CALL_FUNCTION            2
           1488 POP_TOP

598        1490 LOAD_NAME               35 (print)
           1492 LOAD_CONST             134 ('Doge Deposit Wallet :')
           1494 LOAD_GLOBAL             90 (dogewallet)
           1496 CALL_FUNCTION            2
           1498 POP_TOP

599        1500 LOAD_NAME               35 (print)
           1502 LOAD_CONST             135 ('License Type : ')
           1504 LOAD_NAME               91 (logintype)
           1506 CALL_FUNCTION            2
           1508 POP_TOP

600        1510 LOAD_NAME               91 (logintype)
           1512 LOAD_CONST             136 ('Free License')
           1514 COMPARE_OP               2 (==)
           1516 EXTENDED_ARG             6
           1518 POP_JUMP_IF_FALSE     1560

601        1520 LOAD_CONST              62 ('Offline')
           1522 STORE_GLOBAL            92 (statssrv)

602        1524 LOAD_NAME               35 (print)
           1526 LOAD_CONST             137 ('Expired Date : None')
           1528 CALL_FUNCTION            1
           1530 POP_TOP

603        1532 LOAD_NAME               35 (print)
           1534 LOAD_CONST             138 ('SG Server Status :')
           1536 LOAD_NAME               16 (merah)
           1538 LOAD_GLOBAL             92 (statssrv)
           1540 BINARY_ADD
           1542 LOAD_NAME               13 (putih)
           1544 BINARY_ADD
           1546 CALL_FUNCTION            2
           1548 POP_TOP

604        1550 LOAD_NAME               35 (print)
           1552 LOAD_CONST             139 ('Max Balance : 150 DOGE')
           1554 CALL_FUNCTION            1
           1556 POP_TOP
           1558 JUMP_FORWARD            96 (to 1656)

605     >> 1560 LOAD_NAME               91 (logintype)
           1562 LOAD_CONST             140 ('Premium License')
           1564 COMPARE_OP               2 (==)
           1566 EXTENDED_ARG             6
           1568 POP_JUMP_IF_TRUE      1580
           1570 LOAD_NAME               91 (logintype)
           1572 LOAD_CONST             141 ('Platinum License')
           1574 COMPARE_OP               2 (==)
           1576 EXTENDED_ARG             6
           1578 POP_JUMP_IF_FALSE     1656

606     >> 1580 LOAD_CONST             126 ('Online')
           1582 STORE_GLOBAL            92 (statssrv)

607        1584 LOAD_NAME                6 (datetime)
           1586 LOAD_METHOD             93 (now)
           1588 CALL_METHOD              0
           1590 STORE_NAME              94 (mydatetime)

608        1592 LOAD_NAME               35 (print)
           1594 LOAD_CONST             138 ('SG Server Status :')
           1596 LOAD_NAME               15 (hijau)
           1598 LOAD_GLOBAL             92 (statssrv)
           1600 BINARY_ADD
           1602 LOAD_NAME               13 (putih)
           1604 BINARY_ADD
           1606 CALL_FUNCTION            2
           1608 POP_TOP

609        1610 LOAD_NAME               35 (print)
           1612 LOAD_CONST             142 ('Date :')
           1614 LOAD_NAME               94 (mydatetime)
           1616 LOAD_METHOD             95 (strftime)
           1618 LOAD_CONST             143 ('%Y-%m-%d')
           1620 CALL_METHOD              1
           1622 CALL_FUNCTION            2
           1624 POP_TOP

610        1626 LOAD_NAME               35 (print)
           1628 LOAD_CONST             144 ('Expired Date :')
           1630 LOAD_GLOBAL             96 (userdate)
           1632 CALL_FUNCTION            2
           1634 POP_TOP

611        1636 LOAD_NAME               35 (print)
           1638 LOAD_CONST             145 ('Expired In :')
           1640 LOAD_GLOBAL             88 (Expired)
           1642 LOAD_CONST             146 ('Days')
           1644 CALL_FUNCTION            3
           1646 POP_TOP

612        1648 LOAD_NAME               35 (print)
           1650 LOAD_CONST             147 ('Max Balance : Unlimited')
           1652 CALL_FUNCTION            1
           1654 POP_TOP

613     >> 1656 LOAD_NAME               35 (print)
           1658 LOAD_CONST             148 ('Currency Available : DOGE')
           1660 CALL_FUNCTION            1
           1662 POP_TOP
           1664 JUMP_FORWARD            10 (to 1676)

615     >> 1666 LOAD_NAME               35 (print)
           1668 LOAD_CONST             149 ('Information Status Login :')
           1670 LOAD_GLOBAL             60 (statslogin)
           1672 CALL_FUNCTION            2
           1674 POP_TOP

617     >> 1676 LOAD_NAME               35 (print)
           1678 LOAD_NAME               15 (hijau)
           1680 LOAD_CONST             150 ('\nPilih Menu :')
           1682 BINARY_ADD
           1684 CALL_FUNCTION            1
           1686 POP_TOP

618        1688 LOAD_NAME               35 (print)
           1690 LOAD_NAME               14 (kuning)
           1692 LOAD_CONST             151 ('1. Login Premium License')
           1694 BINARY_ADD
           1696 CALL_FUNCTION            1
           1698 POP_TOP

619        1700 LOAD_NAME               35 (print)
           1702 LOAD_CONST             152 ('2. Login For Free')
           1704 CALL_FUNCTION            1
           1706 POP_TOP

620        1708 LOAD_NAME               35 (print)
           1710 LOAD_CONST             153 ('3. Login Platinum License')
           1712 CALL_FUNCTION            1
           1714 POP_TOP

621        1716 LOAD_NAME               35 (print)
           1718 LOAD_CONST             154 ('4. Register Account SELENIA')
           1720 CALL_FUNCTION            1
           1722 POP_TOP

622        1724 LOAD_NAME               35 (print)
           1726 LOAD_CONST             155 ('5. Price List License')
           1728 CALL_FUNCTION            1
           1730 POP_TOP

623        1732 LOAD_NAME               35 (print)
           1734 LOAD_CONST             156 ('0. Keluar')
           1736 CALL_FUNCTION            1
           1738 POP_TOP

624        1740 LOAD_GLOBAL             60 (statslogin)
           1742 LOAD_CONST             126 ('Online')
           1744 COMPARE_OP               2 (==)
           1746 EXTENDED_ARG             6
           1748 POP_JUMP_IF_FALSE     1774

625        1750 LOAD_NAME               35 (print)
           1752 LOAD_CONST             157 ('6. Start Trade')
           1754 CALL_FUNCTION            1
           1756 POP_TOP

626        1758 LOAD_NAME               35 (print)
           1760 LOAD_CONST             158 ('7. Withdraw')
           1762 CALL_FUNCTION            1
           1764 POP_TOP

627        1766 LOAD_NAME               35 (print)
           1768 LOAD_CONST             159 ('8. Account Information')
           1770 CALL_FUNCTION            1
           1772 POP_TOP

629     >> 1774 LOAD_NAME               97 (input)
           1776 LOAD_CONST             160 ('==>')
           1778 CALL_FUNCTION            1
           1780 STORE_NAME              98 (smenu)

630        1782 LOAD_NAME               98 (smenu)
           1784 LOAD_CONST             161 ('1')
           1786 COMPARE_OP               2 (==)
           1788 EXTENDED_ARG             7
           1790 POP_JUMP_IF_FALSE     1820

631        1792 LOAD_CONST               0 (0)
           1794 STORE_NAME              61 (limit)

632        1796 LOAD_CONST             140 ('Premium License')
           1798 STORE_NAME              91 (logintype)

633        1800 LOAD_NAME               65 (login)
           1802 CALL_FUNCTION            0
           1804 POP_TOP

634        1806 LOAD_NAME               68 (verify)
           1808 CALL_FUNCTION            0
           1810 POP_TOP

635        1812 LOAD_NAME               70 (check_license)
           1814 CALL_FUNCTION            0
           1816 POP_TOP
           1818 JUMP_FORWARD            30 (to 1850)

636     >> 1820 LOAD_NAME               98 (smenu)
           1822 LOAD_CONST             162 ('2')
           1824 COMPARE_OP               2 (==)
           1826 EXTENDED_ARG             7
           1828 POP_JUMP_IF_FALSE     1850

637        1830 LOAD_CONST             136 ('Free License')
           1832 STORE_NAME              91 (logintype)

638        1834 LOAD_NAME               65 (login)
           1836 CALL_FUNCTION            0
           1838 POP_TOP

639        1840 LOAD_GLOBAL             86 (dogebalance)
           1842 STORE_NAME              61 (limit)

640        1844 LOAD_NAME               68 (verify)
           1846 CALL_FUNCTION            0
           1848 POP_TOP

641     >> 1850 LOAD_NAME               98 (smenu)
           1852 LOAD_CONST             163 ('3')
           1854 COMPARE_OP               2 (==)
           1856 EXTENDED_ARG             7
           1858 POP_JUMP_IF_FALSE     1888

642        1860 LOAD_CONST               0 (0)
           1862 STORE_NAME              61 (limit)

643        1864 LOAD_CONST             141 ('Platinum License')
           1866 STORE_NAME              91 (logintype)

644        1868 LOAD_NAME               65 (login)
           1870 CALL_FUNCTION            0
           1872 POP_TOP

645        1874 LOAD_NAME               68 (verify)
           1876 CALL_FUNCTION            0
           1878 POP_TOP

646        1880 LOAD_NAME               71 (check_license_platinum)
           1882 CALL_FUNCTION            0
           1884 POP_TOP
           1886 JUMP_FORWARD           172 (to 2060)

647     >> 1888 LOAD_NAME               98 (smenu)
           1890 LOAD_CONST             164 ('4')
           1892 COMPARE_OP               2 (==)
           1894 EXTENDED_ARG             7
           1896 POP_JUMP_IF_FALSE     1906

648        1898 LOAD_NAME               69 (register)
           1900 CALL_FUNCTION            0
           1902 POP_TOP
           1904 JUMP_FORWARD           154 (to 2060)

649     >> 1906 LOAD_NAME               98 (smenu)
           1908 LOAD_CONST             165 ('6')
           1910 COMPARE_OP               2 (==)
           1912 EXTENDED_ARG             7
           1914 POP_JUMP_IF_FALSE     1958
           1916 LOAD_GLOBAL             60 (statslogin)
           1918 LOAD_CONST             126 ('Online')
           1920 COMPARE_OP               2 (==)
           1922 EXTENDED_ARG             7
           1924 POP_JUMP_IF_FALSE     1958

650        1926 LOAD_NAME               91 (logintype)
           1928 LOAD_CONST             136 ('Free License')
           1930 COMPARE_OP               2 (==)
           1932 EXTENDED_ARG             7
           1934 POP_JUMP_IF_FALSE     1948

651        1936 LOAD_NAME               72 (gblnc)
           1938 CALL_FUNCTION            0
           1940 POP_TOP

652        1942 LOAD_GLOBAL             86 (dogebalance)
           1944 STORE_NAME              61 (limit)
           1946 JUMP_FORWARD             0 (to 1948)

655     >> 1948 LOAD_NAME               66 (autobet)
           1950 LOAD_NAME               61 (limit)
           1952 CALL_FUNCTION            1
           1954 POP_TOP
           1956 JUMP_FORWARD           102 (to 2060)

656     >> 1958 LOAD_NAME               98 (smenu)
           1960 LOAD_CONST             166 ('5')
           1962 COMPARE_OP               2 (==)
           1964 EXTENDED_ARG             7
           1966 POP_JUMP_IF_FALSE     1976

657        1968 LOAD_NAME               63 (harga_license)
           1970 CALL_FUNCTION            0
           1972 POP_TOP
           1974 JUMP_FORWARD            84 (to 2060)

658     >> 1976 LOAD_NAME               98 (smenu)
           1978 LOAD_CONST             167 ('7')
           1980 COMPARE_OP               2 (==)
           1982 EXTENDED_ARG             7
           1984 POP_JUMP_IF_FALSE     2004
           1986 LOAD_GLOBAL             60 (statslogin)
           1988 LOAD_CONST             126 ('Online')
           1990 COMPARE_OP               2 (==)
           1992 EXTENDED_ARG             7
           1994 POP_JUMP_IF_FALSE     2004

659        1996 LOAD_NAME               62 (withdraw)
           1998 CALL_FUNCTION            0
           2000 POP_TOP
           2002 JUMP_FORWARD            56 (to 2060)

660     >> 2004 LOAD_NAME               98 (smenu)
           2006 LOAD_CONST             168 ('8')
           2008 COMPARE_OP               2 (==)
           2010 EXTENDED_ARG             7
           2012 POP_JUMP_IF_FALSE     2032
           2014 LOAD_GLOBAL             60 (statslogin)
           2016 LOAD_CONST             126 ('Online')
           2018 COMPARE_OP               2 (==)
           2020 EXTENDED_ARG             7
           2022 POP_JUMP_IF_FALSE     2032

661        2024 LOAD_NAME               67 (ainfo)
           2026 CALL_FUNCTION            0
           2028 POP_TOP
           2030 JUMP_FORWARD            28 (to 2060)

662     >> 2032 LOAD_NAME               98 (smenu)
           2034 LOAD_CONST              36 ('0')
           2036 COMPARE_OP               2 (==)
           2038 EXTENDED_ARG             8
           2040 POP_JUMP_IF_FALSE     2052

663        2042 LOAD_NAME                1 (sys)
           2044 LOAD_METHOD             36 (exit)
           2046 CALL_METHOD              0
           2048 POP_TOP
           2050 JUMP_FORWARD             8 (to 2060)

665     >> 2052 LOAD_NAME               35 (print)
           2054 LOAD_CONST             169 ('NO MENU SELECTED')
           2056 CALL_FUNCTION            1
           2058 POP_TOP
        >> 2060 EXTENDED_ARG             3
           2062 JUMP_ABSOLUTE          910
                try:
                    if Expired <= 0:
                        print(merah + 'License Out of Date' + putih)
                        print(kuning + 'Buy New One' + putih)
                        sys.exit()
                    else:
                        pass
                except:
                    pass
                else:
                    print('Informasi Status Login :', hijau + statslogin + putih)
                    print('Account ID :', accid)
                    print('Username :', Username)
                    print('Doge Balance :', num_format(dogebalance))
                    print('Doge Deposit Wallet :', dogewallet)
                    print('License Type : ', logintype)
                    if logintype == 'Free License':
                        statssrv = 'Offline'
                        print('Expired Date : None')
                        print('SG Server Status :', merah + statssrv + putih)
                        print('Max Balance : 150 DOGE')
                    else:
                        if not logintype == 'Premium License':
                            if logintype == 'Platinum License':
                                pass
                        statssrv = 'Online'
                        mydatetime = datetime.now()
                        print('SG Server Status :', hijau + statssrv + putih)
                        print('Date :', mydatetime.strftime('%Y-%m-%d'))
                        print('Expired Date :', userdate)
                        print('Expired In :', Expired, 'Days')
                        print('Max Balance : Unlimited')
                    print('Currency Available : DOGE')
                    print('Information Status Login :', statslogin)
                    print(hijau + '\nPilih Menu :')
                    print(kuning + '1. Login Premium License')
                    print('2. Login For Free')
                    print('3. Login Platinum License')
                    print('4. Register Account SELENIA')
                    print('5. Price List License')
                    print('0. Keluar')
                    if statslogin == 'Online':
                        print('6. Start Trade')
                        print('7. Withdraw')
                        print('8. Account Information')
                        smenu = input('==>')
                        if smenu == '1':
                            limit = 0
                            logintype = 'Premium License'
                            login()
                            verify()
                            check_license()
                        if smenu == '2':
                            logintype = 'Free License'
                            login()
                            limit = dogebalance
                            verify()
                        if smenu == '3':
                            limit = 0
                            logintype = 'Platinum License'
                            login()
                            verify()
                            check_license_platinum()
                        if smenu == '4':
                            register()
                        if smenu == '6':
                            if statslogin == 'Online':
                                if logintype == 'Free License':
                                    gblnc()
                                    limit = dogebalance
                                else:
                                    pass
                                autobet(limit)
                        if smenu == '5':
                            harga_license()
                        if smenu == '7':
                            if statslogin == 'Online':
                                withdraw()
                        if smenu == '8':
                            if statslogin == 'Online':
                                ainfo()
                        if smenu == '0':
                            sys.exit()
                        print('NO MENU SELECTED')
667     >> 2064 LOAD_CONST               1 (None)
           2066 RETURN_VALUE
